Workbook
Name Segment: #REF!
Name Segment: #REF!
Name Segment: #REF!
Name Segment: #REF!

Sheet COVER SHEET
A1: RSB WORKBOOK
A2: CUSTOMER NAME | B2: LUMOS | E2: ENGINEER | F2: CHAD ROBERTSON
A3: CUSTOMER LOCATION | B3: VIRGINIA | E3: DATE | F3: 46110
A4: MARKET | B4: CHESTERFIELD | E4: Project # | F4: CHST 02-01
C5: Permits Due Date
A6: CAPITAL BUDGET # | B6: =IF(ISBLANK(F4), "", F4) -> CHST 02-01 | C6: Planning Guide #
F7: Cost | G7: Days
A8: Project # | B8: =IF(ISBLANK(F4), "", F4) -> CHST 02-01 | C8: Total Aerial (Eng-Aerial Footage) | D8: =D9+D10 -> 0 | E8: DOT | F8: =LABOR!F49 -> 0
C9: New Aerial Fiber Cable Placement | D9: =SUM(LABOR!B162:B170,LABOR!B200) -> 0 | E9: Municipal | F9: =LABOR!F50 -> 0
C10: Total Overlash | D10: =SUM(LABOR!B176,LABOR!B201,LABOR!B205,LABOR!B206) -> 0 | E10: RR | F10: =LABOR!F51 -> 0
A11: Planned Completion | C11: Total Underground (Eng-New Conduit Footage) | D11: =SUM('LABOR SPAN SHEET'!AD2) -> 10899 | E11: Easement | F11: =TOTALS!C27 -> 0
A12: HLE | C12: Total Existing Conduit Footage | D12: ='LABOR SPAN SHEET'!AA2 -> 0 | E12: Pole | F12: =LABOR!F52 -> 0
A13: Detailed | C13: Total Fiber (Eng-Fiber Footage) | D13: =SUM(MATERIAL!B31:B37,MATERIAL!B107:B113,MATERIAL!B175:B181) -> 17319 | E13: Conduit | F13: =LABOR!F53 -> 0
A14: Job Package | C14: Total Fiber & Conduit (Eng-Total Bld Footage | D14: =D8+D11+D12 -> 10899 | E14: Other | F14: 10000
C15: Variance Approved Dates | E15: Traffic Control | F15: =TOTALS!C30 -> 0
C16: HLE to Detailed Est | E16: Engineering | F16: =SUM(TOTALS!C9:C12) -> 5449.5
A17: Total OSP Cost (- Eng Vendor Cost) | B17: =TOTALS!C71-F16 -> 155279.61 | C17: Detailed Est to JP | E17: Drafting | F17: =SUM(TOTALS!C14:C15) -> 0
A18: Total Including Equ. | B18: =B17+F21 -> 155279.61 | E18: Permitting | F18: =SUM(TOTALS!C17:C28) -> 10000
E19: Construction | F19: =SUM(TOTALS!C32,TOTALS!C35,TOTALS!C37,TOTALS!C40:C41,TOTALS!C44:C45,TOTALS!C48,TOTALS!C52,TOTALS!C64,TOTALS!C66) -> 138776.5
A20: ON NET | B20: QTY | C20: NEAR NET | D20: QTY | E20: Splicing | F20: =SUM(TOTALS!C54,TOTALS!C57,TOTALS!C59,TOTALS!C62) -> 6503.112
A21: SFU Residential-ON | B21: =COUNTIFS('House Count'!F:F, "RES-HOA",'House Count'!H:H,"Y")+COUNTIFS('House Count'!F:F, "RES-SFU",'House Count'!H:H,"Y") -> 17 | C21: SFU Residential-NN | D21: =COUNTIFS('House Count'!F:F, "RES-HOA",'House Count'!H:H,"N")+COUNTIFS('House Count'!F:F, "RES-SFU",'House Count'!H:H,"N") -> 0 | E21: Access Equipment | F21: =TOTALS!C67 -> 0
A22: MDU Residential-ON | B22: =COUNTIFS('House Count'!F:F, "RES-MDU",'House Count'!H:H,"Y") -> 0 | C22: MDU Residential-NN | D22: =COUNTIFS('House Count'!F:F, "RES-MDU",'House Count'!H:H,"N") -> 0 | E22: LCP Equipment | F22: =MATERIAL!H340 -> 0
A23: Business-ON | B23: =COUNTIFS('House Count'!F:F, "COMM-SU",'House Count'!H:H,"Y")+COUNTIFS('House Count'!F:F, "COM-MTU",'House Count'!H:H,"Y") -> 30 | C23: Business-NN | D23: =COUNTIFS('House Count'!F:F, "COMM-SU",'House Count'!H:H,"N")+COUNTIFS('House Count'!F:F, "COM-MTU",'House Count'!H:H,"N") -> 0
A24: Vacant Lots-ON | B24: =COUNTIFS('House Count'!F:F, "VL",'House Count'!H:H,"Y") -> 0 | C24: Vacant Lots-NN | D24: =COUNTIFS('House Count'!F:F, "VL",'House Count'!H:H,"N") -> 23
A25: TOTAL ON NET: | B25: =SUM(B21:B24) -> 47 | C25: TOTAL NEAR NET: | D25: =SUM(D21:D24) -> 23
A27: LIST OF PERMITS - EASEMENTS - IRU SPLICING NEEDED
A28: NAME | B28: DESCRIPTION | E28: DUE | F28: SENT | G28: APPROVED
A38: COMMENTS
A45: *** BELOW IS FOR ADMIN USE ONLY***
A46: JP Approval Date: | C46: Approved By: | E46: Date sent to Construction:
A47: Construction Complete: | D47: Miss Utility Polygon:
A48: REVISION DATE 11/18/2025

Sheet MAP
A1: PASTE LOCATION MAP HERE

Sheet MATERIAL
A1: CUSTOMER NAME | C1: ='COVER SHEET'!B2 -> LUMOS | G1: Tax | H1: 0.05
A2: ENGINEER | C2: ='COVER SHEET'!F2 -> CHAD ROBERTSON | G2: Provisioning | H2: 0.1
A3: Project # | C3: =IF(ISBLANK('COVER SHEET'!F4),"",'COVER SHEET'!F4) -> CHST 02-01
A4: Task Name | B4: QUANTITY | C4: ACTUAL QUANITY | D4: REEL NUMBER | E4: ITEM # | F4: DESCRIPTION | G4: COST | H4: TOTAL
F5: POLE MATERIAL
A6: O.POLES | E6: POLE30C3 | F6: Pole 30' CL3 | G6: 265.72 | H6: =B6*G6 -> 0
A7: O.POLES | E7: POLE30C4 | F7: Pole 30 CL4 | G7: 221.98 | H7: =G7*B7 -> 0
A8: O.POLES | E8: POLE30C5 | F8: Pole 30 CL5 | G8: 195.39 | H8: =B8*G8 -> 0
A9: O.POLES | E9: POLE35C4 | F9: Pole 35 CL4 | G9: 280.86 | H9: =B9*G9 -> 0
A10: O.POLES | E10: POLE35C5 | F10: Pole 35 CL5 | G10: 235.85 | H10: =B10*G10 -> 0
A11: O.POLES | E11: POLE40C2 | F11: Pole 40' CL2 | G11: 395 | H11: =B11*G11 -> 0
A12: O.POLES | E12: POLE40C3 | F12: Pole 40 CL3 | G12: 381.29 | H12: =B12*G12 -> 0
A13: O.POLES | E13: POLE40C4 | F13: Pole 40' CL4 | G13: 325.97 | H13: =B13*G13 -> 0
A14: O.POLES | E14: POLE40C5 | F14: Pole 40' CL5 | G14: 274.22 | H14: =B14*G14 -> 0
A15: O.POLES | E15: POLE45C1 | F15: Pole 45' CL1 Not stocked item, Contact Purchasing for Price/Availability | H15: =B15*G15 -> 0
A16: O.POLES | E16: POLE45C2 | F16: Pole 45' CL2 Not stocked item, Contact Purchasing for Price/Availability | H16: =B16*G16 -> 0
A17: O.POLES | E17: POLE45C3 | F17: Pole 45' CL3 | G17: 480.52 | H17: =B17*G17 -> 0
A18: O.POLES | E18: POLE45C4 | F18: Pole 45' CL4 | G18: 325.97 | H18: =B18*G18 -> 0
A19: O.POLES | E19: POLE50C2 | F19: Pole 50' CL2 | G19: 624.08 | H19: =B19*G19 -> 0
A20: O.POLES | E20: POLE55C1 | F20: Pole 55' CL1 Not stocked item, Contact Purchasing for Price/Availability | H20: =B20*G20 -> 0
A21: O.POLES | E21: POLE55C2 | F21: Pole 55' CL2 | G21: 733.14 | H21: =B21*G21 -> 0
A22: MISC. | H22: =B22*G22 -> 0
A23: MISC. | H23: =B23*G23 -> 0
A24: MISC. | H24: =B24*G24 -> 0
A25: MISC. | H25: =B25*G25 -> 0
F26: SUB-TOTAL - O.POLES | H26: =SUM(H6:H25) -> 0
F27: PROVISIONING - POLE MATERIAL | H27: =H26*(H1+H2) -> 0
F28: TOTAL - O.POLES | H28: =H27+H26 -> 0
A29: <----Click the + to Expand or Collapse the "POLE MATERIAL" Section
B30: - | F30: AERIAL FIBER ASSET MATERIAL
A31: O.FBR.AERL | E31: FIBCOMFIG8 | F31: FIBER - COMMSCOPE FIGURE 8 M-006-MN-8W-F06NS/25G/109 (RDF) | H31: =B31*G31 -> 0
A32: O.FBR.AERL | B32: ='CABLE SHEET'!I3 -> 0 | E32: FIBGEN48ARMR | F32: 048 Loose Tube PN D-048-LA-8W-F12NS; 048ZUC-T4122D20; AT3CEH2YT-048 | G32: 0.31 | H32: =B32*G32 -> 0
A33: O.FBR.AERL | B33: ='CABLE SHEET'!I4 -> 0 | E33: FIBGEN96ARMR | F33: 096 Loose Tube PN D-096-LA-8W-F12NS; 096ZUC-T4122D20; AT3CEH2YT-096 | G33: 0.62 | H33: =B33*G33 -> 0
A34: O.FBR.AERL | B34: ='CABLE SHEET'!I5 -> 0 | E34: FIBGEN144RIB | F34: 144 Ribbon FIber PN 144EC5-14100D53 | G34: 0.98 | H34: =B34*G34 -> 0
A35: O.FBR.AERL | E35: FIBOFS192LTARMR | F35: FIBER OFS AT3CEH2YT-192-FORTEX NON-DIELECTRIC LIGHT ARMOR | H35: =B35*G35 -> 0
A36: O.FBR.AERL | B36: ='CABLE SHEET'!I6 -> 0 | E36: FIBGEN288RIB | F36: 288 Ribbon FIber PN 288EV5-14100D53 | G36: 1.55 | H36: =B36*G36 -> 0
A37: O.FBR.AERL | B37: ='CABLE SHEET'!I7 -> 0 | E37: FIBGEN432RIB | F37: 432 Ribbon Fiber OFS AT-3CE84SX-432; COR 432EV5-14100D53; STL RA0432FSN06TFBUUS | G37: 3.6 | H37: =B37*G37 -> 0
F38: AERIAL CABLE ASSET MATERIAL
A39: O.FBR.AERL | E39: CBLFS2522 | F39: CABLE F.S. 25-22 | H39: =B39*G39 -> 0
A40: O.FBR.AERL | E40: CBLFSKIN10024 | F40: CABLE FOAM SKIN 100-24 | H40: =B40*G40 -> 0
A41: O.FBR.AERL | E41: CBLFSKIN120024 | F41: CABLE FOAM SKIN 1200-24 | H41: =B41*G41 -> 0
A42: O.FBR.AERL | E42: CBLFSKIN1224 | F42: CABLE FOAM SKIN 12-24 | H42: =B42*G42 -> 0
A43: O.FBR.AERL | E43: CBLFSKIN180024 | F43: CABLE FOAM SKIN 1800-24 | H43: =B43*G43 -> 0
A44: O.FBR.AERL | E44: CBLFSKIN20024 | F44: CABLE FOAM SKIN 200-24 | H44: =B44*G44 -> 0
A45: O.FBR.AERL | E45: CBLFSKIN2524 | F45: CABLE FOAM SKIN 25-24 | H45: =B45*G45 -> 0
A46: O.FBR.AERL | E46: CBLFSKIN30024 | F46: CABLE FOAM SKIN 300-24 | H46: =B46*G46 -> 0
A47: O.FBR.AERL | E47: CBLFSKIN40024 | F47: CABLE FOAM SKIN 400-24 | H47: =B47*G47 -> 0
A48: O.FBR.AERL | E48: CBLFSKIN5022 | F48: CABLE FOAM SKIN 50-22 | H48: =B48*G48 -> 0
A49: O.FBR.AERL | E49: CBLFSKIN5024 | F49: CABLE FOAM SKIN 50-24 | H49: =B49*G49 -> 0
A50: O.FBR.AERL | E50: CBLFSKIN60024 | F50: CABLE FOAM SKIN 600-24 | H50: =B50*G50 -> 0
... A73: O.FBR.AERL | E73: CCT5X30TERM | F73: SLIC TERMINAL W/10PR BLK 5X30 W/SPIRAL END - 530-PI-10/SES | H73: =B73*G73 -> 0
H74: =B74*G74 -> 0
F75: AERIAL FIBER SUPPORT PARTS
A76: O.FBR.AERL | E76: SPLSNOSHOE12IN | F76: SNO-SHOE PLASTIC 12" PN FIS12M | G76: 17.5 | H76: =B76*G76 -> 0
A77: O.FBR.AERL | E77: SPLSNOSHOE16 | F77: SNO-SHOE PLASTIC 16" use for 144 fiber count or larger | G77: 34.38 | H77: =B77*G77 -> 0
A78: O.FBR.AERL | E78: HDW10INANCHOR | F78: 10" SCREW ANCHOR | G78: 84.5 | H78: =G78*B78 -> 0
A79: O.FBR.AERL | E79: HDWANCH12HLX | F79: ANCHOR 12" HELIX C102-5206 | H79: =G79*B79 -> 0
A80: O.FBR.AERL | E80: HDWANCH8HLX | F80: ANCHOR 8" HELIX C102-5204 | H80: =G80*B80 -> 0
A81: O.FBR.AERL | E81: HDWTRPLEYENUT | F81: TRIPLEYE EYENUT 12585 | H81: =G81*B81 -> 0
A82: O.FBR.AERL | E82: HDWANCHRD1X7 | F82: ANCHOR ROD 1" X 7' 12334P | H82: =G82*B82 -> 0
F83: AERIAL CLEAR VIEW DROP SINGLE ENDED | H83: =B83*G83 -> 0
A84: O.FBR.AERL | E84: FDPCORCLRCRVOPT75 | F84: FLEX DROP 75' | H84: =B84*G84 -> 0
A85: O.FBR.AERL | E85: FDPCORCLRCRVOPT600 | F85: FLEX DROP 600' | H85: =B85*G85 -> 0
F86: AERIAL MULTI PORT
A87: O.FBR.AERL | E87: HDWWRSTRND14GRN | F87: WIRE #14 STRANDED TRACER GREEN | H87: =B87*G87 -> 0
A88: O.FBR.AERL | E88: FIJSCA | F88: FIBER PIGTAIL 12 FIBER SCAPC RBD9-SA3M | H88: =B88*G88 -> 0
A89: O.FBR.AERL | E89: HDWAHD28PT | F89: AERIAL MOUNTING BRACKET 2-8 PT MOB-KT-AHD 2-8 PORTS | H89: =B89*G89 -> 0
A90: O.FBR.AERL | E90: HDWAHD12PT | F90: AERIAL MOUNTING BRACKET 12 PT MOB-KT-AHD-12 PORTS | H90: =B90*G90 -> 0
A91: O.FBR.AERL | E91: SPLMLTERMBOX | F91: MULTILINK TERM BOX 12"X20"X8" RNB-12208-1SL-C-PG-Y-S | G91: 166.09 | H91: =B91*G91 -> 0
A92: O.FBR.AERL | E92: STRSTRAND516EHS | F92: STRAND 5/16 EHSD | G92: 0.4 | H92: =B92*G92 -> 0
A93: O.FBR.AERL | E93: STRSTRAND14EHS | F93: STRAND 1/4" EHS (6.6M) | G93: 0.26 | H93: =B93*G93 -> 0
A94: O.FBR.AERL | E94: STRSTRAND16M | F94: STRAND 16M 7/16UTL | H94: =B94*G94 -> 0
A95: O.FBR.AERL | E95: HDWSIDEFITPX34A | F95: POLE PLATE SIDEWALK GUY PJ1501 | H95: =B95*G95 -> 0
A96: O.FBR.AERL | E96: HDWGGRDYLW7 | F96: GUY GUARD YELLOW PVC X 7'0 G5517 | G96: 5.95 | H96: =B96*G96 -> 0
A97: O.FBR.AERL | E97: HDWLUMOAERCBLTAG | F97: LUMOS AERIAL CABLE WRAP TAG | G97: 3.29 | H97: =B97*G97 -> 0
A98: O.FBR.AERL | E98: SPLTIITERM24PTSCCON | F98: TII 24 PORT SC-UPC TERMINAL PANEL PN FET3G-24RSCN00 | G98: 133.06 | H98: =B98*G98 -> 0
A99: O.FBR.AERL | E99: SPLSCAPCSMFCON | F99: CONNECTOR SCAPC SPLICE ON F/ 250UM & 900UM 4PK | H99: =B99*G99 -> 0
E100: SPLTII48FGRFET4G | F100: TII 48 PORT OUTDOOR ENCLOSURE | H100: =B100*G100 -> 0
H101: =B101*G287 -> 0
B102: - | F102: TOTAL - O.FBR.AERL | H102: =SUM(H32:H101) -> 0
B103: - | F103: PROVISIONING - O.FBR.AERL | H103: =H102*(H1+H2) -> 0
B104: - | F104: TOTAL - O.FBR.AERL | H104: =H103+H102 -> 0
A105: <----Click the + to Expand or Collapse the "AERIAL FIBER ASSET MATERIAL" Section
F106: UNDERGROUND ASSET MATERIAL
A107: O.FBR.UNDG | B107: ='CABLE SHEET'!N3 -> 0 | E107: FIBGEN48ARMR | F107: 048 Loose Tube PN D-048-LA-8W-F12NS; 048ZUC-T4122D20; AT3CEH2YT-048 | G107: 0.31 | H107: =B107*G107 -> 0
A108: O.FBR.UNDG | E108: FIBGEN72ARMR | F108: 048 Loose Tube PN D-048-LA-8W-F12NS; 048ZUC-T4122D20; AT3CEH2YT-048 | H108: =B108*G108 -> 0
A109: O.FBR.UNDG | B109: ='CABLE SHEET'!N4 -> 0 | E109: FIBGEN96ARMR | F109: 096 Loose Tube PN D-096-LA-8W-F12NS; 096ZUC-T4122D20; AT3CEH2YT-096 | G109: 0.62 | H109: =B109*G109 -> 0
A110: O.FBR.UNDG | B110: ='CABLE SHEET'!N5 -> 0 | E110: FIBGEN144RIB | F110: 144 Ribbon FIber PN 144EC5-14100D53 | G110: 0.98 | H110: =B110*G110 -> 0
A111: O.FBR.UNDG | E111: FIBOFS192LTARMR | F111: FIBER OFS AT3CEH2YT-192-FORTEX NON-DIELECTRIC LIGHT ARMOR | H111: =B111*G111 -> 0
A112: O.FBR.UNDG | B112: ='CABLE SHEET'!N6 -> 0 | E112: FIBGEN288RIB | F112: 288 Ribbon FIber PN 288EV5-14100D53 | G112: 1.55 | H112: =B112*G112 -> 0
A113: O.FBR.UNDG | B113: ='CABLE SHEET'!N7 -> 0 | E113: FIBGEN432RIB | F113: 432 Ribbon Fiber OFS AT-3CE84SX-432; COR 432EV5-14100D53; STL RA0432FSN06TFBUUS | G113: 3.6 | H113: =B113*G113 -> 0
F114: UNDERGROUND CABLE ASSET MATERIAL
A115: O.FBR.UNDG | E115: CBLFS2522 | F115: CABLE F.S. 25-22 | H115: =B115*G115 -> 0
A116: O.FBR.UNDG | E116: CBLFSKIN10024 | F116: CABLE FOAM SKIN 100-24 | H116: =B116*G116 -> 0
A117: O.FBR.UNDG | E117: CBLFSKIN120024 | F117: CABLE FOAM SKIN 1200-24 | H117: =B117*G117 -> 0
A118: O.FBR.UNDG | E118: CBLFSKIN1224 | F118: CABLE FOAM SKIN 12-24 | H118: =B118*G118 -> 0
A119: O.FBR.UNDG | E119: CBLFSKIN180024 | F119: CABLE FOAM SKIN 1800-24 | H119: =B119*G119 -> 0
A120: O.FBR.UNDG | E120: CBLFSKIN20024 | F120: CABLE FOAM SKIN 200-24 | H120: =B120*G120 -> 0
A121: O.FBR.UNDG | E121: CBLFSKIN2524 | F121: CABLE FOAM SKIN 25-24 | H121: =B121*G121 -> 0
A122: O.FBR.UNDG | E122: CBLFSKIN30024 | F122: CABLE FOAM SKIN 300-24 | H122: =B122*G122 -> 0
...

Sheet LABOR
A1: CUSTOMER NAME | C1: - | D1: ='COVER SHEET'!B2 -> LUMOS | E1: Solid Rock Adder
A2: ENGINEER | C2: - | D2: ='COVER SHEET'!F2 -> CHAD ROBERTSON
A3: Project # | C3: - | D3: ='COVER SHEET'!F4 -> CHST 02-01
A5: Task Name | B5: QUANTITY | C5: UNIT | D5: UNIT DESCRIPTION | E5: UNIT COST | F5: TOTAL
B6: =IF(SUM(F29)>0,"-","") -> - | D6: ENGINEERING
D7: PROJECT PLANNING / DESIGN - COMPANY LABOR | E7: 0.7 | F7: =E7*B7 -> 0
D8: PROJECT PLANNING / DESIGN - CONTRACT LABOR | E8: 50 | F8: =E8*B8 -> 0
D9: CONTRACTOR MINIMUM AERIAL/BURIED/UNDERGROUND CHARGE | E9: 1 | F9: =E9*B9 -> 0
D10: CONTRACTOR - FLAT RATE - AERIAL - PER LINEAR FOOT 0-1 MILE | E10: 0.5 | F10: =E10*B10 -> 0
D11: CONTRACTOR - FLAT RATE - AERIAL - PER LINEAR FOOT 1-2 MILE | E11: 0.5 | F11: =E11*B11 -> 0
D12: CONTRACTOR - FLAT RATE - AERIAL - PER LINEAR FOOT 2-5 MILE | E12: 0.5 | F12: =E12*B12 -> 0
D13: CONTRACTOR - FLAT RATE - BURIED/UNDERGROUND - PER LINEAR FOOT 0-1 MILE | E13: 0.5 | F13: =E13*B13 -> 0
D14: CONTRACTOR - FLAT RATE - BURIED/UNDERGROUND - PER LINEAR FOOT 1-2 MILE | E14: 0.5 | F14: =E14*B14 -> 0
B15: =SUM('LABOR SPAN SHEET'!AD2) -> 10899 | D15: CONTRACTOR - FLAT RATE - BURIED/UNDERGROUND - PER LINEAR FOOT 2-5 MILE | E15: 0.5 | F15: =E15*B15 -> 5449.5
D16: CONTRACTOR - DESIGN OVER 5 MILES - PER BID | F16: =E16*B16 -> 0
D17: CONTRACTOR - MAJOR REDESIGN COST - PER FOOT | E17: 0.6 | F17: =E17*B17 -> 0
D18: CONTRACTOR - PE STAMP - PLUS 15% OF COST | F18: =E18*B18 -> 0
D19: CONTRACTOR - OSP OFFICE ESTIMATE | E19: 150 | F19: =E19*B19 -> 0
D20: CONTRACTOR - OSP DETAILED FIELD ESTIMATE | E20: 350 | F20: =E20*B20 -> 0
D21: CONTRACTOR - CAP RING - SHORT HAUL - LONG HAUL - FIELD ESTIMATE | E21: 500 | F21: =E21*B21 -> 0
D22: CONTRACTOR - PROJECT MANAGEMENT | E22: 48 | F22: =E22*B22 -> 0
D23: CONTRACTOR - OSP ENGINEER | E23: 48 | F23: =E23*B23 -> 0
D24: CONTRACTOR - ASSOCIATE ENGINEER | E24: 37 | F24: =E24*B24 -> 0
D25: CONTRACTOR - ENGINEER ASSISTANT | E25: 21 | F25: =E25*B25 -> 0
D26: CONTRACTOR - ENGINEERING ADMIN | E26: 29 | F26: =E26*B26 -> 0
D27: CONTRACTOR - ENGINEERING ADMIN ASSISTANT | E27: 21 | F27: =E27*B27 -> 0
D28: LUMOS LABOR - JOB COORDINATION - PROJECT MANAGEMENT | E28: 500 | F28: =E28*B28 -> 0
D29: TOTAL - ENGINEERING | F29: =SUM(F7:F28) -> 5449.5
A30: <----Click the + to Expand or Collapse the "ENGINEERING" Section
B31: =IF(SUM(F35)>0,"-","") | D31: DRAFTING
D32: CONTRACTOR - CAD INPUT / MAPPING (M4) | E32: 32 | F32: =E32*B32 -> 0
D33: COMPANY LABOR - CAD INPUT/ MAPPING (M4) | F33: =E33*B33 -> 0
D34: CONTRACTOR - M4 - POSTING TIME | E34: 150 | F34: =E34*B34 -> 0
D35: TOTAL - DRAFTING | F35: =SUM(F32:F34) -> 0
A36: <----Click the + to Expand or Collapse the "DRAFTING" Section
B37: =IF(SUM(F56)>0,"-","") -> - | D37: PERMITTING
D38: EASEMENTS / ACQUISITION - COMPANY LABOR | E38: 50 | F38: =E38*B38 -> 0
D39: EASEMENTS / ACQUISITION - CONTRACT LABOR | E39: 50 | F39: =E39*B39 -> 0
D40: CONTRACTOR - NEGOTIATION OF EASEMENT BEYOND FIRST ATTEMPT | E40: 500 | F40: =E40*B40 -> 0
D41: CONTRACTOR - NEGOTIATION OF BUILDING LICENSE AGREEMENTS | E41: 500 | F41: =E41*B41 -> 0
B42: =IF(SUM(F42)>0,"-","") | D42: EASEMENT FEES | E42: 0 | F42: =E42 -> 0
D43: PERMITS / AUTHORIZATION - COMPANY LABOR | E43: 50 | F43: =E43*B43 -> 0
D44: PERMITS / AUTHORIZATION - CONTRACT LABOR | E44: 610 | F44: =E44*B44 -> 0
D45: ADMINISTRATION PERMITING TIME - COMPANY LABOR | E45: 300 | F45: =E45*B45 -> 0
D46: ADMINISTRATION PERMITING TIME - CONTRACT LABOR | E46: 300 | F46: =E46*B46 -> 0
D47: CONTRACTOR - SPECIALIZED PERMITS | E47: 625 | F47: =E47*B47 -> 0
D48: CONTRACTOR - PE STAMP - PLUS 15% OF COST | E48: 600 | F48: =E48*B48 -> 0
D49: PERMIT FEES - DOT | E49: 175 | F49: =E49*B49 -> 0
D50: PERMIT FEES - MUNICIPAL | E50: 50 | F50: =E50*B50 -> 0
D51: PERMIT FEES - RR | E51: 350 | F51: =E51*B51 -> 0
D52: PERMIT FEES - POLE | E52: 0 | F52: =E52*B52 -> 0
D53: PERMIT FEES - CONDUIT | E53: 0 | F53: =E53*B53 -> 0
D54: PERMIT FEES - OTHER | E54: 10000 | F54: =E54 -> 10000
D55: PERMIT FEES - TRAFFIC CONTROL (ENGINEERING DESIGN) | E55: 0 | F55: =E55 -> 0
D56: TOTAL - PERMITTING | F56: =SUM(F38:F55) -> 10000
A57: <----Click the + to Expand or Collapse the "PERMITTING" Section
B58: =IF(SUM(F139)>0,"-","") | D58: POLES
A59: O.POLES | C59: 100 | D59: PLACE POLE - 30 TO 35 FT. | E59: 250 | F59: =E59*B59 -> 0
A60: O.POLES | C60: 105 | D60: PLACE POLE 40 TO 45 FT | E60: 315 | F60: =E60*B60 -> 0
A61: O.POLES | C61: 110 | D61: PLACE POLE - 50 TO 55 FT. | E61: 350 | F61: =E61*B61 -> 0
A62: O.POLES | C62: 115 | D62: PLACE POLE 60 AND ABOVE FT | E62: 395 | F62: =E62*B62 -> 0
A63: O.POLES | C63: 120 | D63: PLACE STUB POLE | E63: 155 | F63: =E63*B63 -> 0
A64: O.POLES | C64: 125 | D64: REMOVE POLE 20 TO 35 FT. | E64: 70 | F64: =E64*B64 -> 0
A65: O.POLES | C65: 130 | D65: REMOVE POLE 40 TO 45 FT. | E65: 80 | F65: =E65*B65 -> 0
A66: O.POLES | C66: 135 | D66: REMOVE POLE 50 TO 55 FT. | E66: 100 | F66: =E66*B66 -> 0
A67: O.POLES | C67: 140 | D67: REMOVE POLE 60 AND ABOVE FT | E67: 120 | F67: =E67*B67 -> 0
A68: O.POLES | C68: 145 | D68: REMOVE STUB POLE | E68: 65 | F68: =E68*B68 -> 0
A69: O.POLES | C69: 150 | D69: ADDITIONAL CHARGE POLE SET IN POWER | E69: 150 | F69: =E69*B69 -> 0
A70: O.POLES | C70: 151 | D70: HAND SET POLE | E70: 300 | F70: =E70*B70 -> 0
... A134: O.POLES | C134: 625 | D134: Straighten Pole | E134: 130 | F134: =E134*B134 -> 0
A135: O.POLES | C135: 670 | D135: Right - Of - Way Clearing HOURLY | F135: =E135*B135 -> 0
A136: O.POLES | C136: 671 | D136: Cut/trim trees w/ Bucket Truck HOURLY | F136: =E136*B136 -> 0
A137: O.POLES | C137: 672 | D137: Cut/trim trees w/ Bucket Truck & Chipper HOURLY | F137: =E137*B137 -> 0
A138: O.POLES | C138: 673 | D138: Remove large trees 8" or larger at per tree basis HOURLY | F138: =E138*B138 -> 0
D139: TOTAL - PLACE POLE | F139: =SUM(F59:F138) -> 0
A140: <----Click the + to Expand or Collapse the "POLES" Section
B141: =IF(SUM(F159)>0,"-","") | D141: POLES
A142: O.POLES | C142: 101 | D142: PLACE POLE - 25 TO 40 FT. | E142: 350 | F142: =E142*B142 -> 0
A143: O.POLES | C143: 102 | D143: PLACE POLE - 45 TO 55 FT. | E143: 425 | F143: =E143*B143 -> 0
A144: O.POLES | C144: 103 | D144: PLACE POLE - > 55 FT | E144: 515 | F144: =E144*B144 -> 0
A145: O.POLES | C145: 106 | D145: REMOVE POLE 30 TO 40 FT. | E145: 215 | F145: =E145*B145 -> 0
A146: O.POLES | C146: 108 | D146: REMOVE POLE 45 TO 55 FT. | E146: 215 | F146: =E146*B146 -> 0
A147: O.POLES | C147: 110 | D147: PLACE STRAND (PRE-APPROVED) | E147: 2.5 | F147: =E147*B147 -> 0
A148: O.POLES | C148: 111 | D148: ADDITIONAL CHARGE POLE SET IN POWER | E148: 175 | F148: =E148*B148 -> 0
A149: O.POLES | C149: 112 | D149: HAND SET POLE | E149: 600 | F149: =E149*B149 -> 0
A150: O.POLES | C150: 113 | D150: RESTORE PAVEMENT AT POLE PLACE | E150: 75 | F150: =E150*B150 -> 0
A151: O.POLES | C151: 114 | D151: REPLACE PAVEMENT AT POLE REMOVAL | E151: 75 | F151: =E151*B151 -> 0
A152: O.POLES | C152: 115 | D152: ROCK REMOVAL POLE CU FT PRICE | E152: 100 | F152: =E152*B152 -> 0
A153: O.POLES | C153: 116 | D153: HAND DIG POLE | E153: 165 | F153: =E153*B153 -> 0
... A156: O.POLES | C156: 144 | D156: Hand Set Push Brace | E156: 220 | F156: =E156*B156 -> 0
A157: O.POLES | C157: MISC
A158: O.POLES | C158: MISC
D159: TOTAL - PLACE POLE | F159: =SUM(F142:F158) -> 0
A160: <----Click the + to Expand or Collapse the "POLES" Section
B161: =IF(SUM(F185)>0,"-","") | D161: AERIAL
A162: O.FBR.AERL | C162: 420 | D162: Place Aerial Cable (4 to 30 Fiber) (Cable Handling and Figure Eighting included) | E162: 1.06 | F162: =E162*B162 -> 0
A163: O.FBR.AERL | C163: 421 | D163: Place Aerial RDF or ADSS (6-24 Fiber) (Includes Cable Attachment to Wood Pole) | E163: 1.08 | F163: =E163*B163 -> 0
A164: O.FBR.AERL | C164: 425 | D164: Place Aerial Cable (36 to 72 Fiber) (Cable Handling and Figure eighting included) | E164: 1.18 | F164: =E164*B164 -> 0
A165: O.FBR.AERL | C165: 430 | D165: Place Aerial Cable (96 to 288 Fiber) (Cable Handling and Figure eighting included) | E165: 1.26 | F165: =E165*B165 -> 0
A166: O.CBL.AERL | C166: 435 | D166: Place Aerial Cable (12 to 200 Copper) | E166: 0.8 | F166: =E166*B166 -> 0
...

Sheet TOTALS
A1: NAME | B1: ='COVER SHEET'!B2:D2 -> LUMOS
A2: LOCATION | B2: ='COVER SHEET'!B3:D3 -> VIRGINIA
A3: Project # | B3: ='COVER SHEET'!F4 -> CHST 02-01
A4: MetaSolv # | B4: ='COVER SHEET'!B9 -> 0
A5: DDID # | B5: =RIGHT(B3,5) -> 02-01
A6: CODE | B6: DESCRIPTION | C6: AMOUNT
B7: ENGINEERING
B8: PROJECT PLANNING / DESIGN
B9: Project Planning / Design - Contract Labor | C9: =SUM(LABOR!F8:F27) -> 5449.5
B10: Project Planning / Design - Company Labor | C10: =LABOR!F7 -> 0
B11: Misc. Copper Splicing Labor | C11: =LABOR!F385 -> 0
B12: Job Coordination/Lumos Labor | C12: =LABOR!F28 -> 0
B13: JOB PRINTS / DRAFTING
B14: Job Prints / Mapping - Contract Labor | C14: =SUM(LABOR!F32,LABOR!F34) -> 0
B15: Job Prints/ Mapping - Company Labor | C15: =LABOR!F33 -> 0
B16: PERMITS AND AUTHORIZATION
B17: Permits / Authorization - Contract Labor | C17: =LABOR!F44 -> 0
B18: Permits / Authorization - Company Labor | C18: =LABOR!F43 -> 0
B19: Easements / Acquisition - Contract Labor | C19: =LABOR!F39 -> 0
B20: Easements / Acquisition - Company Labor | C20: =LABOR!F38 -> 0
B21: CONTRACTOR - NEGOTIATION OF EASEMENT BEYOND FIRST ATTEMPT | C21: =LABOR!F40 -> 0
B22: CONTRACTOR - NEGOTIATION OF BUILDING LICENSE AGREEMENTS | C22: =LABOR!F41 -> 0
B23: CONTRACTOR - SPECIALIZED PERMITS | C23: =LABOR!F47 -> 0
B24: CONTRACTOR - PE STAMP - PLUS 15% OF COST | C24: =LABOR!F48 -> 0
B25: Administration Permitting Time - Company Labor | C25: =LABOR!F45 -> 0
B26: Administration Permitting Time - Contract Labor | C26: =LABOR!F46 -> 0
B27: Easement Fees | C27: =LABOR!F42 -> 0
B28: Permit Fees | C28: =SUM(LABOR!F49:F54) -> 10000
B29: PROJECT PLANNING / CONSTRUCTION / ADMIN
B30: TRAFFIC CONTROL | C30: =PERMITS!P88 -> 0
B31: PLACE POLE
A32: O.POLES | B32: Contractor Labor | C32: =SUM(LABOR!F139,LABOR!F159) -> 0
A33: O.POLES | B33: Material - Pole | C33: =MATERIAL!H26 -> 0
A34: O.POLES | B34: Provisioning - Pole Material | C34: =MATERIAL!H27 -> 0
A35: O.POLES | B35: Total + Tax - Pole Material | C35: =MATERIAL!H28 -> 0
B36: PLACE CABLE
A37: O.FBR.AERL | B37: Contractor Labor - Aerial Fiber | C37: =SUM(LABOR!F185,LABOR!F216) -> 0
A38: O.FBR.AERL | B38: Material - Aerial Fiber | C38: =MATERIAL!H102 -> 0
A39: O.FBR.AERL | B39: Provisioning - Aerial Material | C39: =MATERIAL!H103 -> 0
A40: O.FBR.AERL | B40: Total + Tax - Aerial Material | C40: =MATERIAL!H104 -> 0
A41: O.FBR.UNDG | B41: Contractor Labor - Underground | C41: =SUM(LABOR!F243,LABOR!F262) -> 0
A42: O.FBR.UNDG | B42: Material - Underground | C42: =MATERIAL!H170 -> 0
A43: O.FBR.UNDG | B43: Provisioning - Underground Material | C43: =MATERIAL!H171 -> 0
A44: O.FBR.UNDG | B44: Total + Tax - Underground Material | C44: =MATERIAL!H172 -> 0
A45: O.FBR.BURD | B45: Contractor Labor - Buried | C45: =SUM(LABOR!F307,LABOR!F339) -> 103540.5
A46: O.FBR.BURD | B46: Material - Buried | C46: =MATERIAL!H238 -> 14924.12
A47: O.FBR.BURD | B47: Provisioning - Buried Material | C47: =MATERIAL!H239 -> 2238.618
A48: O.FBR.BURD | B48: Total + Tax - Buried Material | C48: =MATERIAL!H240 -> 17162.738
B49: PLACE CONDUIT
A50: O.CONDUIT | B50: Material - Buried Fiber | C50: =MATERIAL!H268 -> 15715.88
A51: O.CONDUIT | B51: Provisioning - Conduit Material | C51: =MATERIAL!H269 -> 2357.382
A52: O.CONDUIT | B52: Total + Tax - Conduit Material | C52: =MATERIAL!H270 -> 18073.262
B53: AFO SPLICE
A54: O.FBR.AERL | B54: Lumos Labor - Splice Aerial Fiber | C54: =LABOR!F386 -> 0
A55: O.FBR.AERL | B55: Material - Aerial Fiber | C55: =MATERIAL!H292 -> 0
A56: O.FBR.AERL | B56: Provisioning - Aerial Splicing Material | C56: =MATERIAL!H293 -> 0
A57: O.FBR.AERL | B57: Total + Tax - Aerial Splicing Material | C57: =MATERIAL!H294 -> 0
B58: ONE COMM SPLICE
A59: O.FBR.UNDG | B59: Lumos Labor - Splice Underground Fiber | C59: =LABOR!F426 -> 0
A60: O.FBR.UNDG | B60: Material - Underground Fiber | C60: =MATERIAL!H319 -> 5654.88
A61: O.FBR.UNDG | B61: Provisioning - Underground Splicing Material | C61: =MATERIAL!H320 -> 848.232
A62: O.FBR.UNDG | B62: Total + Tax - Underground Splicing Material | C62: =MATERIAL!H321 -> 6503.112
B63: MISCELLANEOUS LABOR
A64: MISC. | B64: Total - MISCELLANEOUS LABOR | C64: =LABOR!F466 -> 0
B65: ACCESS EQUIPMENT
B66: PLACE FTTP EQUIP | C66: =LABOR!F438 -> 0
B67: HLE ACCESS EQUIP. | C67: =PERMITS!G70 -> 0
B68: DROPS | C68: =SUM(MATERIAL!H157:H158,MATERIAL!H84:H85,MATERIAL!H225:H226) -> 0
B69: ONT'S | C69: =SUM(MATERIAL!H338:H340) -> 0
A70: S.D.EQ | B70: TOTAL ACCESS EQUIPMENT | C70: =MATERIAL!H346 -> 0
B71: TOTAL JOB COST | C71: =SUM(C9:C28,C30:C32,C35,C37,C40,C41,C44,C45,C48,C52,C54,C57,C59,C62,C64,C66,C70) -> 160729.11

Sheet CABLE SHEET
B1: Method | C1: New Conduit | G1: Method | H1: Aerial | L1: Method | M1: Existing Conduit
B2: Cable Size | C2: 24 | D2: =SUMIFS($C$13:$DV$13,$C$9:$DV$9,C1,$C$12:$DV$12,C2) -> 0 | G2: Cable Size | H2: 24 | I2: =SUMIFS($C$13:$BD$13,$C$9:$BD$9,H1,$C$12:$BD$12,H2) -> 0 | L2: Cable Size | M2: 24 | N2: =SUMIFS($C$13:$BD$13,$C$9:$BD$9,M1,$C$12:$BD$12,M2) -> 0 | Q2: 15 FOR SPLT
C3: 48 | D3: =SUMIFS($C$13:$DV$13,$C$9:$DV$9,C1,$C$12:$DV$12,C3) -> 7927 | H3: 48 | I3: =SUMIFS($C$13:$BD$13,$C$9:$BD$9,H1,$C$12:$BD$12,H3) -> 0 | M3: 48 | N3: =SUMIFS($C$13:$BD$13,$C$9:$BD$9,M1,$C$12:$BD$12,M3) -> 0 | Q3: 50 FOR ALL ELSE
C4: 96 | D4: =SUMIFS($C$13:$DV$13,$C$9:$DV$9,C1,$C$12:$DV$12,C4) -> 3394 | H4: 96 | I4: =SUMIFS($C$13:$BD$13,$C$9:$BD$9,H1,$C$12:$BD$12,H4) -> 0 | M4: 96 | N4: =SUMIFS($C$13:$BD$13,$C$9:$BD$9,M1,$C$12:$BD$12,M4) -> 0 | Q4: FIRST ROW 0 AND THE HANDHOLE STORAGE OF HH IT STARTS FROM
C5: 144 | D5: =SUMIFS($C$13:$DV$13,$C$9:$DV$9,C1,$C$12:$DV$12,C5) -> 5998 | H5: 144 | I5: =SUMIFS($C$13:$BD$13,$C$9:$BD$9,H1,$C$12:$BD$12,H5) -> 0 | M5: 144 | N5: =SUMIFS($C$13:$BD$13,$C$9:$BD$9,M1,$C$12:$BD$12,M5) -> 0
C6: 288 | D6: =SUMIFS($C$13:$DV$13,$C$9:$DV$9,C1,$C$12:$DV$12,C6) -> 0 | H6: 288 | I6: =SUMIFS($C$13:$BD$13,$C$9:$BD$9,H1,$C$12:$BD$12,H6) -> 0 | M6: 288 | N6: =SUMIFS($C$13:$BD$13,$C$9:$BD$9,M1,$C$12:$BD$12,M6) -> 0
C7: 432 | D7: =SUMIFS($C$13:$DF$13,$C$9:$DF$9,C1,$C$12:$DF$12,C7) -> 0 | H7: 432 | I7: =SUMIFS($C$13:$DF$13,$C$9:$DF$9,H1,$C$12:$DF$12,H7) -> 0 | M7: 432 | N7: =SUMIFS($C$13:$DF$13,$C$9:$DF$9,M1,$C$12:$DF$12,M7) -> 0
B9: SEG 1 | C9: New Conduit | G9: SEG 2 | H9: New Conduit | L9: SEG 3 | M9: New Conduit | Q9: SEG 4 | R9: New Conduit | V9: SEG 5 | W9: New Conduit | AA9: SEG 6 | AB9: New Conduit | AF9: SEG 7 | AG9: New Conduit | AK9: SEG 8 | AL9: New Conduit | AP9: SEG 9 | AQ9: New Conduit | AU9: SEG 10 | AV9: New Conduit | AZ9: SEG 11 | BA9: New Conduit | BE9: SEG 12 | BF9: New Conduit | BJ9: SEG 13 | BK9: New Conduit | BO9: SEG 14 | BP9: New Conduit | BT9: SEG 15 | BU9: New Conduit | BY9: SEG 16 | BZ9: New Conduit | CD9: SEG 17 | CE9: New Conduit | CI9: SEG 18 | CJ9: New Conduit | CN9: SEG 19 | CO9: New Conduit | CS9: SEG 20 | CT9: New Conduit | CX9: SEG 21 | CY9: New Conduit | DC9: SEG 22 | DD9: New Conduit | DH9: SEG 23 | DI9: New Conduit | DM9: SEG 24 | DR9: SEG 25
B10: START | C10: 351 EAST HUNDRED RD | G10: START | H10: 351 EAST HUNDRED RD | L10: START | M10: 351 EAST HUNDRED RD | Q10: START | R10: 351 EAST HUNDRED RD | V10: START | W10: 351 EAST HUNDRED RD | AA10: START | AB10: 115 EAST HUNDRED RD | AF10: START | AG10: 3 EAST HUNDRED RD | AK10: START | AL10: 350 EAST HUNDRED RD | AP10: START | AQ10: 348 EAST HUNDRED RD | AU10: START | AV10: 350 EAST HUNDRED RD | AZ10: START | BA10: 431 EAST HUNDRED RD | BE10: START | BJ10: START | BO10: START | BT10: START | BY10: START | CD10: START | CI10: START | CN10: START | CS10: START | CX10: START | DC10: START | DH10: START | DM10: START | DR10: START
B11: END | C11: 3 EAST HUNDRED RD | G11: END | H11: 13312 BERMUDA ORCHARD LN | L11: END | M11: 3 EAST HUNDRED RD | Q11: END | R11: 350 EAST HUNDRED RD | V11: END | W11: 13312 BERMUDA ORCHARD LN | AA11: END | AB11: 13320 INGE RD | AF11: END | AG11: 3 EAST HUNDRED RD | AK11: END | AL11: 348 EAST HUNDRED RD | AP11: END | AQ11: 100 EAST HUNDRED RD | AU11: END | AV11: 600 EAST HUNDRED RD | AZ11: END | BA11: 804 EAST HUNDRED RD | BE11: END | BJ11: END | BO11: END | BT11: END | BY11: END | CD11: END | CI11: END | CN11: END | CS11: END | CX11: END | DC11: END | DH11: END | DM11: END | DR11: END
B12: CABLE SIZE | C12: 96 | G12: CABLE SIZE | H12: 144 | L12: CABLE SIZE | M12: 144 | Q12: CABLE SIZE | R12: 144 | V12: CABLE SIZE | W12: 144 | AA12: CABLE SIZE | AB12: 48 | AF12: CABLE SIZE | AG12: 48 | AK12: CABLE SIZE | AL12: 96 | AP12: CABLE SIZE | AQ12: 48 | AU12: CABLE SIZE | AV12: 48 | AZ12: CABLE SIZE | BA12: 48 | BE12: CABLE SIZE | BJ12: CABLE SIZE | BO12: CABLE SIZE | BT12: CABLE SIZE | BY12: CABLE SIZE | CD12: CABLE SIZE | CI12: CABLE SIZE | CN12: CABLE SIZE | CS12: CABLE SIZE | CX12: CABLE SIZE | DC12: CABLE SIZE | DH12: CABLE SIZE | DM12: CABLE SIZE | DR12: CABLE SIZE
B13: TOTAL | C13: =SUM(C15:E201) -> 2588 | G13: TOTAL | H13: =SUM(H15:J201) -> 1433 | L13: TOTAL | M13: =SUM(M15:O201) -> 2831 | Q13: TOTAL | R13: =SUM(R15:T201) -> 301 | V13: TOTAL | W13: =SUM(W15:Y201) -> 1433 | AA13: TOTAL | AB13: =SUM(AB15:AD201) -> 610 | AF13: TOTAL | AG13: =SUM(AG15:AI201) -> 293 | AK13: TOTAL | AL13: =SUM(AL15:AN201) -> 806 | AP13: TOTAL | AQ13: =SUM(AQ15:AS201) -> 1207 | AU13: TOTAL | AV13: =SUM(AV15:AX201) -> 2590 | AZ13: TOTAL | BA13: =SUM(BA15:BC201) -> 3227 | BE13: TOTAL | BF13: =SUM(BF15:BH201) -> 0 | BJ13: TOTAL | BK13: =SUM(BK15:BM201) -> 0 | BO13: TOTAL | BP13: =SUM(BP15:BR201) -> 0 | BT13: TOTAL | BU13: =SUM(BU15:BW201) -> 0 | BY13: TOTAL | BZ13: =SUM(BZ15:CB201) -> 0 | CD13: TOTAL | CE13: =SUM(CE15:CG201) -> 0 | CI13: TOTAL | CJ13: =SUM(CJ15:CL201) -> 0 | CN13: TOTAL | CO13: =SUM(CO15:CQ201) -> 0 | CS13: TOTAL | CT13: =SUM(CT15:CV201) -> 0 | CX13: TOTAL | CY13: =SUM(CY15:DA201) -> 0 | DC13: TOTAL | DD13: =SUM(DD15:DF201) -> 0 | DH13: TOTAL | DI13: =SUM(DI15:DK201) -> 0 | DM13: TOTAL | DN13: =SUM(DN15:DP201) -> 0 | DR13: TOTAL | DS13: =SUM(DS15:DU201) -> 0
C14: SPAN | D14: STORAGE | E14: RISER | H14: SPAN | I14: STORAGE | J14: RISER | M14: SPAN | N14: STORAGE | O14: RISER | R14: SPAN | S14: STORAGE | T14: RISER | W14: SPAN | X14: STORAGE | Y14: RISER | AB14: SPAN | AC14: STORAGE | AD14: RISER | AG14: SPAN | AH14: STORAGE | AI14: RISER | AL14: SPAN | AM14: STORAGE | AN14: RISER | AQ14: SPAN | AR14: STORAGE | AS14: RISER | AV14: SPAN | AW14: STORAGE | AX14: RISER | BA14: SPAN | BB14: STORAGE | BC14: RISER | BF14: SPAN | BG14: STORAGE | BH14: RISER | BK14: SPAN | BL14: STORAGE | BM14: RISER | BP14: SPAN | BQ14: STORAGE | BR14: RISER | BU14: SPAN | BV14: STORAGE | BW14: RISER | BZ14: SPAN | CA14: STORAGE | CB14: RISER | CE14: SPAN | CF14: STORAGE | CG14: RISER | CJ14: SPAN | CK14: STORAGE | CL14: RISER | CO14: SPAN | CP14: STORAGE | CQ14: RISER | CT14: SPAN | CU14: STORAGE | CV14: RISER | CY14: SPAN | CZ14: STORAGE | DA14: RISER | DD14: SPAN | DE14: STORAGE | DF14: RISER | DI14: SPAN | DJ14: STORAGE | DK14: RISER | DN14: SPAN | DO14: STORAGE | DP14: RISER | DS14: SPAN | DT14: STORAGE | DU14: RISER
C15: 0 | D15: 50 | H15: 0 | I15: 50 | M15: 0 | N15: 50 | R15: 0 | S15: 50 | W15: 0 | X15: 50 | AB15: 0 | AC15: 50 | AG15: 0 | AH15: 50 | AL15: 0 | AM15: 50 | AQ15: 0 | AR15: 50 | AV15: 0 | AW15: 50 | BA15: 0
C16: 459 | D16: 15 | H16: 102 | I16: 15 | M16: 459 | N16: 15 | R16: 201 | S16: 50 | W16: 102 | X16: 15 | AB16: 269 | AC16: 15 | AG16: 228 | AH16: 15 | AL16: 105 | AM16: 15 | AQ16: 356 | AR16: 15 | AV16: 323 | AW16: 15 | BA16: 273
C17: 404 | D17: 15 | H17: 323 | I17: 15 | M17: 404 | N17: 15 | W17: 323 | X17: 15 | AB17: 261 | AC17: 15 | AL17: 586 | AM17: 50 | AQ17: 342 | AR17: 15 | AV17: 213 | AW17: 15 | BA17: 500
C18: 461 | D18: 15 | H18: 434 | I18: 15 | M18: 461 | N18: 15 | W18: 434 | X18: 15 | AQ18: 414 | AR18: 15 | AV18: 420 | AW18: 15 | BA18: 499
C19: 39 | D19: 50 | H19: 163 | I19: 50 | M19: 39 | N19: 50 | W19: 163 | X19: 50 | AV19: 373 | AW19: 15 | BA19: 538
C20: 109 | D20: 50 | H20: 251 | I20: 15 | M20: 109 | N20: 50 | W20: 251 | X20: 15 | AV20: 360 | AW20: 15 | BA20: 374
C21: 285 | D21: 50 | M21: 285 | N21: 50 | AV21: 761 | AW21: 15 | BA21: 313
C22: 242 | D22: 15 | M22: 242 | N22: 15 | BA22: 388
C23: 314 | D23: 15 | M23: 314 | N23: 15 | BA23: 57
M24: 228 | N24: 15 | BA24: 183
BA25: 102

Sheet LABOR SPAN SHEET
J1: UNIT 140 NEW AERIAL | K1: UNIT 141 OVERLASH | L1: UNIT 141 OVERLASH | M1: UNIT 141 OVERLASH | N1: UNIT 146 OL MP ONLY | O1: UNIT 148 PLACE RDF or SELFSUPPORT MP TAIL | Q1: TOTAL FOOTAGE UNIT 147 | S1: =SUM(Q2:Y2) -> 0 | AA1: UNIT 220 | AB1: UNIT 210 | AD1: UNIT 200 | AE1: UNIT 5 | AF1: UNIT 5
C2: TOTAL FOOTAGES | J2: =SUM(J7:J1000) -> 0 | K2: =SUM(K7:K1000) -> 0 | L2: =SUM(L7:L1000) -> 0 | M2: =SUM(M7:M1000) -> 0 | N2: =SUM(N7:N1000) -> 0 | O2: =SUM(O7:O1000) -> 0 | P2: TOTAL SPAN * NUMBER MP | Q2: =Q3*Q4 -> 0 | R2: =R3*R4 -> 0 | S2: =S3*S4 -> 0 | T2: =T3*T4 -> 0 | U2: =U3*U4 -> 0 | V2: =V3*V4 -> 0 | W2: =W3*W4 -> 0 | X2: =X3*X4 -> 0 | Y2: =Y3*Y4 -> 0 | AA2: =SUM(AA7:AA1000) -> 0 | AB2: =SUM(AB7:AB1000) -> 0 | AD2: =SUM(AD7:AD1000) -> 10899 | AE2: =SUM(AE7:AE1000) -> 0 | AF2: =SUM(AF7:AF1000) -> 0 | AG2: =SUM(AG7:AG1000) -> 14636
P3: SPAN FOOTAGE | Q3: =SUM(Q7:Q404) -> 0 | R3: =SUM(R7:R404) -> 0 | S3: =SUM(S7:S404) -> 0 | T3: =SUM(T7:T404) -> 0 | U3: =SUM(U7:U404) -> 0 | V3: =SUM(V7:V404) -> 0 | W3: =SUM(W7:W404) -> 0 | X3: =SUM(X7:X404) -> 0 | Y3: =SUM(Y7:Y404) -> 0 | BZ3: 1 | CB3: 1
P4: NUMBER OF MP PER SPAN | Q4: 1 | R4: 2 | S4: 3 | T4: 4 | U4: 5 | V4: 6 | W4: 7 | X4: 8 | Y4: 9 | BZ4: 2 | CB4: 2
K5: CABLE ONLY OR WITH MP TAILS | M5: MPS 2 AND 3 | N5: USE FOR 1ST MP | Q5: THESE COUNTS ARE AFTER SUBTRACTING 2 MP'S THAT WOULD BE INCLUDED WITH NEW BUILD OR OVBER LASH. OR AFTER THE FIRST MP ONLY OVERLASH. COUNTING ONLY UNIT 127 | AD5: UNIT 200 | AE5: UNIT 5 | AF5: UNIT 5
A6: JOB PRINT PAGE # | B6: Construction Note Letter Job Print | C6: SPAN FOOTAGE | D6: NON-STANDARD CONDUIT SIZE | E6: IS THIS A PARALLELING DROP CONDUIT? | F6: CABLES THIS SPAN | G6: NEW CONDUIT THIS SPAN ONLY (UP TO 2) | H6: *ADDITIONAL* NEW CONDUIT 3RD & 4TH CONDUIT (UP TO 2) | I6: *ADDITIONAL* NEW CONDUIT 5TH CONDUIT (UP TO 1) | J6: NEW AERIAL Cable INCLUDES 2 MP TAILS | K6: OVERLASH CABLE INCLUDES 2 MP TAILS | L6: OVERLASH 2ND CABLE | M6: OVERLASH MPS ONLY (USE FOR MP 2 AND 3) | N6: OVERLASH MP TAIL ONLY 1ST MP TAIL | O6: SELF SUPPORT MP TAILS OR RDF | Q6: 1 MP | R6: 2 MP'S | S6: 3 MP'S | T6: 4 MP'S | U6: 5 MP'S | V6: 6 MP'S | W6: 7 MP'S | X6: 8 MP'S | Y6: 9 MP'S | AA6: PULL IN EXISTING CONDUIT | AB6: PULL ADDITIONAL FIBER (AFTER 2ND FIBER) | AD6: NEW BURIED (INCLUDES UP TO 2 CONDUITS) | AE6: *ADDITIONAL* NEW BURIED (INCLUDES 3RD AND 4TH CONDUITS) | AF6: *ADDITIONAL* NEW BURIED (5TH CONDUIT) | AG6: CONDUIT MATERIAL QUANTITY TO BE ORDERED
A7: SP-1 | B7: A | C7: 102 | E7: NO | F7: 2 | G7: 1 | H7: 0 | AA7: =IF(G7=0, IF(OR(H7>0,F7>0),C7*F7,""),"") | AB7: =IF(G7>=1,IF(F7>1,C7*(F7-2),""),"") -> 0 | AD7: =IF(E7="YES",IF(G7=1,"",""),IF(G7=1,C7,IF(G7=2,C7,IF(G7=0,"","")))) -> 102 | AE7: =IF(E7="YES",IF(G7=1,"",IF(H7=1,C7,"")),IF(H7=1,C7,IF(H7=2,C7,IF(H7=0,"","")))) | AF7: =IF(E7="YES",IF(I7=1,C7,""),IF(I7=1,C7,IF(I7=2,C7,IF(I7=0,"","")))) | AG7: =(C7*G7)+(C7*H7)+(C7*I7) -> 102
A8: SP-1 | B8: B | C8: 113 | E8: NO | F8: 2 | G8: 2 | H8: 0 | AA8: =IF(G8=0, IF(OR(H8>0,F8>0),C8*F8,""),"") | AB8: =IF(G8>=1,IF(F8>1,C8*(F8-2),""),"") -> 0 | AD8: =IF(E8="YES",IF(G8=1,"",""),IF(G8=1,C8,IF(G8=2,C8,IF(G8=0,"","")))) -> 113 | AE8: =IF(E8="YES",IF(G8=1,"",IF(H8=1,C8,"")),IF(H8=1,C8,IF(H8=2,C8,IF(H8=0,"","")))) | AF8: =IF(E8="YES",IF(I8=1,C8,""),IF(I8=1,C8,IF(I8=2,C8,IF(I8=0,"","")))) | AG8: =(C8*G8)+(C8*H8)+(C8*I8) -> 226
A9: SP-1 | B9: C | C9: 106 | E9: NO | F9: 2 | G9: 1 | H9: 0 | AA9: =IF(G9=0, IF(OR(H9>0,F9>0),C9*F9,""),"") | AB9: =IF(G9>=1,IF(F9>1,C9*(F9-2),""),"") -> 0 | AD9: =IF(E9="YES",IF(G9=1,"",""),IF(G9=1,C9,IF(G9=2,C9,IF(G9=0,"","")))) -> 106 | AE9: =IF(E9="YES",IF(G9=1,"",IF(H9=1,C9,"")),IF(H9=1,C9,IF(H9=2,C9,IF(H9=0,"","")))) | AF9: =IF(E9="YES",IF(I9=1,C9,""),IF(I9=1,C9,IF(I9=2,C9,IF(I9=0,"","")))) | AG9: =(C9*G9)+(C9*H9)+(C9*I9) -> 106
A10: SP-1 | B10: D | C10: 459 | E10: NO | F10: 2 | G10: 1 | H10: 0 | AA10: =IF(G10=0, IF(OR(H10>0,F10>0),C10*F10,""),"") | AB10: =IF(G10>=1,IF(F10>1,C10*(F10-2),""),"") -> 0 | AD10: =IF(E10="YES",IF(G10=1,"",""),IF(G10=1,C10,IF(G10=2,C10,IF(G10=0,"","")))) -> 459 | AE10: =IF(E10="YES",IF(G10=1,"",IF(H10=1,C10,"")),IF(H10=1,C10,IF(H10=2,C10,IF(H10=0,"","")))) | AF10: =IF(E10="YES",IF(I10=1,C10,""),IF(I10=1,C10,IF(I10=2,C10,IF(I10=0,"","")))) | AG10: =(C10*G10)+(C10*H10)+(C10*I10) -> 459
A11: SP-2 | B11: A | C11: 182 | E11: NO | F11: 1 | G11: 1 | H11: 0 | AA11: =IF(G11=0, IF(OR(H11>0,F11>0),C11*F11,""),"") | AB11: =IF(G11>=1,IF(F11>1,C11*(F11-2),""),"") | AD11: =IF(E11="YES",IF(G11=1,"",""),IF(G11=1,C11,IF(G11=2,C11,IF(G11=0,"","")))) -> 182 | AE11: =IF(E11="YES",IF(G11=1,"",IF(H11=1,C11,"")),IF(H11=1,C11,IF(H11=2,C11,IF(H11=0,"","")))) | AF11: =IF(E11="YES",IF(I11=1,C11,""),IF(I11=1,C11,IF(I11=2,C11,IF(I11=0,"","")))) | AG11: =(C11*G11)+(C11*H11)+(C11*I11) -> 182
A12: SP-2 | B12: B | C12: 323 | E12: NO | F12: 1 | G12: 1 | H12: 0 | AA12: =IF(G12=0, IF(OR(H12>0,F12>0),C12*F12,""),"") | AB12: =IF(G12>=1,IF(F12>1,C12*(F12-2),""),"") | AD12: =IF(E12="YES",IF(G12=1,"",""),IF(G12=1,C12,IF(G12=2,C12,IF(G12=0,"","")))) -> 323 | AE12: =IF(E12="YES",IF(G12=1,"",IF(H12=1,C12,"")),IF(H12=1,C12,IF(H12=2,C12,IF(H12=0,"","")))) | AF12: =IF(E12="YES",IF(I12=1,C12,""),IF(I12=1,C12,IF(I12=2,C12,IF(I12=0,"","")))) | AG12: =(C12*G12)+(C12*H12)+(C12*I12) -> 323
A13: SP-2 | B13: C | C13: 105 | E13: NO | F13: 1 | G13: 1 | H13: 0 | AA13: =IF(G13=0, IF(OR(H13>0,F13>0),C13*F13,""),"") | AB13: =IF(G13>=1,IF(F13>1,C13*(F13-2),""),"") | AD13: =IF(E13="YES",IF(G13=1,"",""),IF(G13=1,C13,IF(G13=2,C13,IF(G13=0,"","")))) -> 105 | AE13: =IF(E13="YES",IF(G13=1,"",IF(H13=1,C13,"")),IF(H13=1,C13,IF(H13=2,C13,IF(H13=0,"","")))) | AF13: =IF(E13="YES",IF(I13=1,C13,""),IF(I13=1,C13,IF(I13=2,C13,IF(I13=0,"","")))) | AG13: =(C13*G13)+(C13*H13)+(C13*I13) -> 105
A14: SP-2 | B14: D | C14: 404 | E14: NO | F14: 1 | G14: 1 | H14: 0 | AA14: =IF(G14=0, IF(OR(H14>0,F14>0),C14*F14,""),"") | AB14: =IF(G14>=1,IF(F14>1,C14*(F14-2),""),"") | AD14: =IF(E14="YES",IF(G14=1,"",""),IF(G14=1,C14,IF(G14=2,C14,IF(G14=0,"","")))) -> 404 | AE14: =IF(E14="YES",IF(G14=1,"",IF(H14=1,C14,"")),IF(H14=1,C14,IF(H14=2,C14,IF(H14=0,"","")))) | AF14: =IF(E14="YES",IF(I14=1,C14,""),IF(I14=1,C14,IF(I14=2,C14,IF(I14=0,"","")))) | AG14: =(C14*G14)+(C14*H14)+(C14*I14) -> 404
A15: SP-3 | B15: A | C15: 404 | E15: NO | F15: 2 | G15: 1 | H15: 0 | AA15: =IF(G15=0, IF(OR(H15>0,F15>0),C15*F15,""),"") | AB15: =IF(G15>=1,IF(F15>1,C15*(F15-2),""),"") -> 0 | AD15: =IF(E15="YES",IF(G15=1,"",""),IF(G15=1,C15,IF(G15=2,C15,IF(G15=0,"","")))) -> 404 | AE15: =IF(E15="YES",IF(G15=1,"",IF(H15=1,C15,"")),IF(H15=1,C15,IF(H15=2,C15,IF(H15=0,"","")))) | AF15: =IF(E15="YES",IF(I15=1,C15,""),IF(I15=1,C15,IF(I15=2,C15,IF(I15=0,"","")))) | AG15: =(C15*G15)+(C15*H15)+(C15*I15) -> 404
A16: SP-4 | B16: A | C16: 182 | E16: YES | F16: 1 | G16: 2 | H16: 0 | AA16: =IF(G16=0, IF(OR(H16>0,F16>0),C16*F16,""),"") | AB16: =IF(G16>=1,IF(F16>1,C16*(F16-2),""),"") | AD16: =IF(E16="YES",IF(G16=1,"",""),IF(G16=1,C16,IF(G16=2,C16,IF(G16=0,"","")))) | AE16: =IF(E16="YES",IF(G16=1,"",IF(H16=1,C16,"")),IF(H16=1,C16,IF(H16=2,C16,IF(H16=0,"","")))) | AF16: =IF(E16="YES",IF(I16=1,C16,""),IF(I16=1,C16,IF(I16=2,C16,IF(I16=0,"","")))) | AG16: =(C16*G16)+(C16*H16)+(C16*I16) -> 364
A17: SP-4 | B17: B | C17: 356 | E17: NO | F17: 1 | G17: 1 | H17: 0 | AA17: =IF(G17=0, IF(OR(H17>0,F17>0),C17*F17,""),"") | AB17: =IF(G17>=1,IF(F17>1,C17*(F17-2),""),"") | AD17: =IF(E17="YES",IF(G17=1,"",""),IF(G17=1,C17,IF(G17=2,C17,IF(G17=0,"","")))) -> 356 | AE17: =IF(E17="YES",IF(G17=1,"",IF(H17=1,C17,"")),IF(H17=1,C17,IF(H17=2,C17,IF(H17=0,"","")))) | AF17: =IF(E17="YES",IF(I17=1,C17,""),IF(I17=1,C17,IF(I17=2,C17,IF(I17=0,"","")))) | AG17: =(C17*G17)+(C17*H17)+(C17*I17) -> 356
A18: SP-4 | B18: C | C18: 461 | E18: NO | F18: 2 | G18: 1 | H18: 0 | AA18: =IF(G18=0, IF(OR(H18>0,F18>0),C18*F18,""),"") | AB18: =IF(G18>=1,IF(F18>1,C18*(F18-2),""),"") -> 0 | AD18: =IF(E18="YES",IF(G18=1,"",""),IF(G18=1,C18,IF(G18=2,C18,IF(G18=0,"","")))) -> 461 | AE18: =IF(E18="YES",IF(G18=1,"",IF(H18=1,C18,"")),IF(H18=1,C18,IF(H18=2,C18,IF(H18=0,"","")))) | AF18: =IF(E18="YES",IF(I18=1,C18,""),IF(I18=1,C18,IF(I18=2,C18,IF(I18=0,"","")))) | AG18: =(C18*G18)+(C18*H18)+(C18*I18) -> 461
... A58: SP-19 | B58: D | C58: 197 | E58: YES | F58: 0 | G58: 1 | H58: 0 | AA58: =IF(G58=0, IF(OR(H58>0,F58>0),C58*F58,""),"") | AB58: =IF(G58>=1,IF(F58>1,C58*(F58-2),""),"") | AD58: =IF(E58="YES",IF(G58=1,"",""),IF(G58=1,C58,IF(G58=2,C58,IF(G58=0,"","")))) | AE58: =IF(E58="YES",IF(G58=1,"",IF(H58=1,C58,"")),IF(H58=1,C58,IF(H58=2,C58,IF(H58=0,"","")))) | AF58: =IF(E58="YES",IF(I58=1,C58,""),IF(I58=1,C58,IF(I58=2,C58,IF(I58=0,"","")))) | AG58: =(C58*G58)+(C58*H58)+(C58*I58) -> 197
AA59: =IF(G59=0, IF(OR(H59>0,F59>0),C59*F59,""),"") | AB59: =IF(G59>=1,IF(F59>1,C59*(F59-2),""),"") | AD59: =IF(E59="YES",IF(G59=1,"",""),IF(G59=1,C59,IF(G59=2,C59,IF(G59=0,"","")))) | AE59: =IF(E59="YES",IF(G59=1,"",IF(H59=1,C59,"")),IF(H59=1,C59,IF(H59=2,C59,IF(H59=0,"","")))) | AF59: =IF(E59="YES",IF(I59=1,C59,""),IF(I59=1,C59,IF(I59=2,C59,IF(I59=0,"","")))) | AG59: =(C59*G59)+(C59*H59)+(C59*I59) -> 0
AA60: =IF(G60=0, IF(OR(H60>0,F60>0),C60*F60,""),"") | AB60: =IF(G60>=1,IF(F60>1,C60*(F60-2),""),"") | AD60: =IF(E60="YES",IF(G60=1,"",""),IF(G60=1,C60,IF(G60=2,C60,IF(G60=0,"","")))) | AE60: =IF(E60="YES",IF(G60=1,"",IF(H60=1,C60,"")),IF(H60=1,C60,IF(H60=2,C60,IF(H60=0,"","")))) | AF60: =IF(E60="YES",IF(I60=1,C60,""),IF(I60=1,C60,IF(I60=2,C60,IF(I60=0,"","")))) | AG60: =(C60*G60)+(C60*H60)+(C60*I60) -> 0
AA61: =IF(G61=0, IF(OR(H61>0,F61>0),C61*F61,""),"") | AB61: =IF(G61>=1,IF(F61>1,C61*(F61-2),""),"") | AD61: =IF(E61="YES",IF(G61=1,"",""),IF(G61=1,C61,IF(G61=2,C61,IF(G61=0,"","")))) | AE61: =IF(E61="YES",IF(G61=1,"",IF(H61=1,C61,"")),IF(H61=1,C61,IF(H61=2,C61,IF(H61=0,"","")))) | AF61: =IF(E61="YES",IF(I61=1,C61,""),IF(I61=1,C61,IF(I61=2,C61,IF(I61=0,"","")))) | AG61: =(C61*G61)+(C61*H61)+(C61*I61) -> 0
AA62: =IF(G62=0, IF(OR(H62>0,F62>0),C62*F62,""),"") | AB62: =IF(G62>=1,IF(F62>1,C62*(F62-2),""),"") | AD62: =IF(E62="YES",IF(G62=1,"",""),IF(G62=1,C62,IF(G62=2,C62,IF(G62=0,"","")))) | AE62: =IF(E62="YES",IF(G62=1,"",IF(H62=1,C62,"")),IF(H62=1,C62,IF(H62=2,C62,IF(H62=0,"","")))) | AF62: =IF(E62="YES",IF(I62=1,C62,""),IF(I62=1,C62,IF(I62=2,C62,IF(I62=0,"","")))) | AG62: =(C62*G62)+(C62*H62)+(C62*I62) -> 0
AA63: =IF(G63=0, IF(OR(H63>0,F63>0),C63*F63,""),"") | AB63: =IF(G63>=1,IF(F63>1,C63*(F63-2),""),"") | AD63: =IF(E63="YES",IF(G63=1,"",""),IF(G63=1,C63,IF(G63=2,C63,IF(G63=0,"","")))) | AE63: =IF(E63="YES",IF(G63=1,"",IF(H63=1,C63,"")),IF(H63=1,C63,IF(H63=2,C63,IF(H63=0,"","")))) | AF63: =IF(E63="YES",IF(I63=1,C63,""),IF(I63=1,C63,IF(I63=2,C63,IF(I63=0,"","")))) | AG63: =(C63*G63)+(C63*H63)+(C63*I63) -> 0
AA64: =IF(G64=0, IF(OR(H64>0,F64>0),C64*F64,""),"") | AB64: =IF(G64>=1,IF(F64>1,C64*(F64-2),""),"") | AD64: =IF(E64="YES",IF(G64=1,"",""),IF(G64=1,C64,IF(G64=2,C64,IF(G64=0,"","")))) | AE64: =IF(E64="YES",IF(G64=1,"",IF(H64=1,C64,"")),IF(H64=1,C64,IF(H64=2,C64,IF(H64=0,"","")))) | AF64: =IF(E64="YES",IF(I64=1,C64,""),IF(I64=1,C64,IF(I64=2,C64,IF(I64=0,"","")))) | AG64: =(C64*G64)+(C64*H64)+(C64*I64) -> 0
AA65: =IF(G65=0, IF(OR(H65>0,F65>0),C65*F65,""),"") | AB65: =IF(G65>=1,IF(F65>1,C65*(F65-2),""),"") | AD65: =IF(E65="YES",IF(G65=1,"",""),IF(G65=1,C65,IF(G65=2,C65,IF(G65=0,"","")))) | AE65: =IF(E65="YES",IF(G65=1,"",IF(H65=1,C65,"")),IF(H65=1,C65,IF(H65=2,C65,IF(H65=0,"","")))) | AF65: =IF(E65="YES",IF(I65=1,C65,""),IF(I65=1,C65,IF(I65=2,C65,IF(I65=0,"","")))) | AG65: =(C65*G65)+(C65*H65)+(C65*I65) -> 0
AA66: =IF(G66=0, IF(OR(H66>0,F66>0),C66*F66,""),"") | AB66: =IF(G66>=1,IF(F66>1,C66*(F66-2),""),"") | AD66: =IF(E66="YES",IF(G66=1,"",""),IF(G66=1,C66,IF(G66=2,C66,IF(G66=0,"","")))) | AE66: =IF(E66="YES",IF(G66=1,"",IF(H66=1,C66,"")),IF(H66=1,C66,IF(H66=2,C66,IF(H66=0,"","")))) | AF66: =IF(E66="YES",IF(I66=1,C66,""),IF(I66=1,C66,IF(I66=2,C66,IF(I66=0,"","")))) | AG66: =(C66*G66)+(C66*H66)+(C66*I66) -> 0
AA67: =IF(G67=0, IF(OR(H67>0,F67>0),C67*F67,""),"") | AB67: =IF(G67>=1,IF(F67>1,C67*(F67-2),""),"") | AD67: =IF(E67="YES",IF(G67=1,"",""),IF(G67=1,C67,IF(G67=2,C67,IF(G67=0,"","")))) | AE67: =IF(E67="YES",IF(G67=1,"",IF(H67=1,C67,"")),IF(H67=1,C67,IF(H67=2,C67,IF(H67=0,"","")))) | AF67: =IF(E67="YES",IF(I67=1,C67,""),IF(I67=1,C67,IF(I67=2,C67,IF(I67=0,"","")))) | AG67: =(C67*G67)+(C67*H67)+(C67*I67) -> 0
AA68: =IF(G68=0, IF(OR(H68>0,F68>0),C68*F68,""),"") | AB68: =IF(G68>=1,IF(F68>1,C68*(F68-2),""),"") | AD68: =IF(E68="YES",IF(G68=1,"",""),IF(G68=1,C68,IF(G68=2,C68,IF(G68=0,"","")))) | AE68: =IF(E68="YES",IF(G68=1,"",IF(H68=1,C68,"")),IF(H68=1,C68,IF(H68=2,C68,IF(H68=0,"","")))) | AF68: =IF(E68="YES",IF(I68=1,C68,""),IF(I68=1,C68,IF(I68=2,C68,IF(I68=0,"","")))) | AG68: =(C68*G68)+(C68*H68)+(C68*I68) -> 0
AA69: =IF(G69=0, IF(OR(H69>0,F69>0),C69*F69,""),"") | AB69: =IF(G69>=1,IF(F69>1,C69*(F69-2),""),"") | AD69: =IF(E69="YES",IF(G69=1,"",""),IF(G69=1,C69,IF(G69=2,C69,IF(G69=0,"","")))) | AE69: =IF(E69="YES",IF(G69=1,"",IF(H69=1,C69,"")),IF(H69=1,C69,IF(H69=2,C69,IF(H69=0,"","")))) | AF69: =IF(E69="YES",IF(I69=1,C69,""),IF(I69=1,C69,IF(I69=2,C69,IF(I69=0,"","")))) | AG69: =(C69*G69)+(C69*H69)+(C69*I69) -> 0
AA70: =IF(G70=0, IF(OR(H70>0,F70>0),C70*F70,""),"") | AB70: =IF(G70>=1,IF(F70>1,C70*(F70-2),""),"") | AD70: =IF(E70="YES",IF(G70=1,"",""),IF(G70=1,C70,IF(G70=2,C70,IF(G70=0,"","")))) | AE70: =IF(E70="YES",IF(G70=1,"",IF(H70=1,C70,"")),IF(H70=1,C70,IF(H70=2,C70,IF(H70=0,"","")))) | AF70: =IF(E70="YES",IF(I70=1,C70,""),IF(I70=1,C70,IF(I70=2,C70,IF(I70=0,"","")))) | AG70: =(C70*G70)+(C70*H70)+(C70*I70) -> 0
... AA1342: =IF(G1342=0, IF(OR(H1342>0,F1342>0),C1342*F1342,""),"") | AB1342: =IF(G1342>=1,IF(F1342>1,C1342*(F1342-2),""),"") | AD1342: =IF(E1342="YES",IF(G1342=1,"",""),IF(G1342=1,C1342,IF(G1342=2,C1342,IF(G1342=0,"","")))) | AE1342: =IF(E1342="YES",IF(G1342=1,"",IF(H1342=1,C1342,"")),IF(H1342=1,C1342,IF(H1342=2,C1342,IF(H1342=0,"","")))) | AF1342: =IF(E1342="YES",IF(I1342=1,C1342,""),IF(I1342=1,C1342,IF(I1342=2,C1342,IF(I1342=0,"","")))) | AG1342: =(C1342*G1342)+(C1342*H1342)+(C1342*I1342) -> 0
AB1343: =IF(G1343>=1,IF(F1343>1,C1343*(F1343-2),""),"") | AD1343: =IF(E1343="YES",IF(G1343=1,"",""),IF(G1343=1,C1343,IF(G1343=2,C1343,IF(G1343=0,"","")))) | AE1343: =IF(E1343="YES",IF(G1343=1,"",IF(H1343=1,C1343,"")),IF(H1343=1,C1343,IF(H1343=2,C1343,IF(H1343=0,"","")))) | AF1343: =IF(E1343="YES",IF(I1343=1,C1343,""),IF(I1343=1,C1343,IF(I1343=2,C1343,IF(I1343=0,"","")))) | AG1343: =(C1343*G1343)+(C1343*H1343)+(C1343*I1343) -> 0
AB1344: =IF(G1344>=1,IF(F1344>1,C1344*(F1344-2),""),"") | AD1344: =IF(E1344="YES",IF(G1344=1,"",""),IF(G1344=1,C1344,IF(G1344=2,C1344,IF(G1344=0,"","")))) | AE1344: =IF(E1344="YES",IF(G1344=1,"",IF(H1344=1,C1344,"")),IF(H1344=1,C1344,IF(H1344=2,C1344,IF(H1344=0,"","")))) | AF1344: =IF(E1344="YES",IF(I1344=1,C1344,""),IF(I1344=1,C1344,IF(I1344=2,C1344,IF(I1344=0,"","")))) | AG1344: =(C1344*G1344)+(C1344*H1344)+(C1344*I1344) -> 0
AB1345: =IF(G1345>=1,IF(F1345>1,C1345*(F1345-2),""),"") | AD1345: =IF(E1345="YES",IF(G1345=1,"",""),IF(G1345=1,C1345,IF(G1345=2,C1345,IF(G1345=0,"","")))) | AE1345: =IF(E1345="YES",IF(G1345=1,"",IF(H1345=1,C1345,"")),IF(H1345=1,C1345,IF(H1345=2,C1345,IF(H1345=0,"","")))) | AF1345: =IF(E1345="YES",IF(I1345=1,C1345,""),IF(I1345=1,C1345,IF(I1345=2,C1345,IF(I1345=0,"","")))) | AG1345: =(C1345*G1345)+(C1345*H1345)+(C1345*I1345) -> 0
AB1346: =IF(G1346>=1,IF(F1346>1,C1346*(F1346-2),""),"") | AD1346: =IF(E1346="YES",IF(G1346=1,"",""),IF(G1346=1,C1346,IF(G1346=2,C1346,IF(G1346=0,"","")))) | AE1346: =IF(E1346="YES",IF(G1346=1,"",IF(H1346=1,C1346,"")),IF(H1346=1,C1346,IF(H1346=2,C1346,IF(H1346=0,"","")))) | AF1346: =IF(E1346="YES",IF(I1346=1,C1346,""),IF(I1346=1,C1346,IF(I1346=2,C1346,IF(I1346=0,"","")))) | AG1346: =(C1346*G1346)+(C1346*H1346)+(C1346*I1346) -> 0
AB1347: =IF(G1347>=1,IF(F1347>1,C1347*(F1347-2),""),"") | AD1347: =IF(E1347="YES",IF(G1347=1,"",""),IF(G1347=1,C1347,IF(G1347=2,C1347,IF(G1347=0,"","")))) | AE1347: =IF(E1347="YES",IF(G1347=1,"",IF(H1347=1,C1347,"")),IF(H1347=1,C1347,IF(H1347=2,C1347,IF(H1347=0,"","")))) | AF1347: =IF(E1347="YES",IF(I1347=1,C1347,""),IF(I1347=1,C1347,IF(I1347=2,C1347,IF(I1347=0,"","")))) | AG1347: =(C1347*G1347)+(C1347*H1347)+(C1347*I1347) -> 0
AB1348: =IF(G1348>=1,IF(F1348>1,C1348*(F1348-2),""),"") | AD1348: =IF(E1348="YES",IF(G1348=1,"",""),IF(G1348=1,C1348,IF(G1348=2,C1348,IF(G1348=0,"","")))) | AE1348: =IF(E1348="YES",IF(G1348=1,"",IF(H1348=1,C1348,"")),IF(H1348=1,C1348,IF(H1348=2,C1348,IF(H1348=0,"","")))) | AF1348: =IF(E1348="YES",IF(I1348=1,C1348,""),IF(I1348=1,C1348,IF(I1348=2,C1348,IF(I1348=0,"","")))) | AG1348: =(C1348*G1348)+(C1348*H1348)+(C1348*I1348) -> 0
AB1349: =IF(G1349>=1,IF(F1349>1,C1349*(F1349-2),""),"") | AD1349: =IF(E1349="YES",IF(G1349=1,"",""),IF(G1349=1,C1349,IF(G1349=2,C1349,IF(G1349=0,"","")))) | AE1349: =IF(E1349="YES",IF(G1349=1,"",IF(H1349=1,C1349,"")),IF(H1349=1,C1349,IF(H1349=2,C1349,IF(H1349=0,"","")))) | AF1349: =IF(E1349="YES",IF(I1349=1,C1349,""),IF(I1349=1,C1349,IF(I1349=2,C1349,IF(I1349=0,"","")))) | AG1349: =(C1349*G1349)+(C1349*H1349)+(C1349*I1349) -> 0
AB1350: =IF(G1350>=1,IF(F1350>1,C1350*(F1350-2),""),"") | AD1350: =IF(E1350="YES",IF(G1350=1,"",""),IF(G1350=1,C1350,IF(G1350=2,C1350,IF(G1350=0,"","")))) | AE1350: =IF(E1350="YES",IF(G1350=1,"",IF(H1350=1,C1350,"")),IF(H1350=1,C1350,IF(H1350=2,C1350,IF(H1350=0,"","")))) | AF1350: =IF(E1350="YES",IF(I1350=1,C1350,""),IF(I1350=1,C1350,IF(I1350=2,C1350,IF(I1350=0,"","")))) | AG1350: =(C1350*G1350)+(C1350*H1350)+(C1350*I1350) -> 0
AB1351: =IF(G1351>=1,IF(F1351>1,C1351*(F1351-2),""),"") | AD1351: =IF(E1351="YES",IF(G1351=1,"",""),IF(G1351=1,C1351,IF(G1351=2,C1351,IF(G1351=0,"","")))) | AE1351: =IF(E1351="YES",IF(G1351=1,"",IF(H1351=1,C1351,"")),IF(H1351=1,C1351,IF(H1351=2,C1351,IF(H1351=0,"","")))) | AF1351: =IF(E1351="YES",IF(I1351=1,C1351,""),IF(I1351=1,C1351,IF(I1351=2,C1351,IF(I1351=0,"","")))) | AG1351: =(C1351*G1351)+(C1351*H1351)+(C1351*I1351) -> 0
AB1352: =IF(G1352>=1,IF(F1352>1,C1352*(F1352-2),""),"") | AD1352: =IF(E1352="YES",IF(G1352=1,"",""),IF(G1352=1,C1352,IF(G1352=2,C1352,IF(G1352=0,"","")))) | AE1352: =IF(E1352="YES",IF(G1352=1,"",IF(H1352=1,C1352,"")),IF(H1352=1,C1352,IF(H1352=2,C1352,IF(H1352=0,"","")))) | AF1352: =IF(E1352="YES",IF(I1352=1,C1352,""),IF(I1352=1,C1352,IF(I1352=2,C1352,IF(I1352=0,"","")))) | AG1352: =(C1352*G1352)+(C1352*H1352)+(C1352*I1352) -> 0
AB1353: =IF(G1353>=1,IF(F1353>1,C1353*(F1353-2),""),"") | AD1353: =IF(E1353="YES",IF(G1353=1,"",""),IF(G1353=1,C1353,IF(G1353=2,C1353,IF(G1353=0,"","")))) | AE1353: =IF(E1353="YES",IF(G1353=1,"",IF(H1353=1,C1353,"")),IF(H1353=1,C1353,IF(H1353=2,C1353,IF(H1353=0,"","")))) | AF1353: =IF(E1353="YES",IF(I1353=1,C1353,""),IF(I1353=1,C1353,IF(I1353=2,C1353,IF(I1353=0,"","")))) | AG1353: =(C1353*G1353)+(C1353*H1353)+(C1353*I1353) -> 0
AB1354: =IF(G1354>=1,IF(F1354>1,C1354*(F1354-2),""),"") | AD1354: =IF(E1354="YES",IF(G1354=1,"",""),IF(G1354=1,C1354,IF(G1354=2,C1354,IF(G1354=0,"","")))) | AE1354: =IF(E1354="YES",IF(G1354=1,"",IF(H1354=1,C1354,"")),IF(H1354=1,C1354,IF(H1354=2,C1354,IF(H1354=0,"","")))) | AF1354: =IF(E1354="YES",IF(I1354=1,C1354,""),IF(I1354=1,C1354,IF(I1354=2,C1354,IF(I1354=0,"","")))) | AG1354: =(C1354*G1354)+(C1354*H1354)+(C1354*I1354) -> 0
... AB1381: =IF(G1381>=1,IF(F1381>1,C1381*(F1381-2),""),"") | AD1381: =IF(E1381="YES",IF(G1381=1,"",""),IF(G1381=1,C1381,IF(G1381=2,C1381,IF(G1381=0,"","")))) | AE1381: =IF(E1381="YES",IF(G1381=1,"",IF(H1381=1,C1381,"")),IF(H1381=1,C1381,IF(H1381=2,C1381,IF(H1381=0,"","")))) | AF1381: =IF(E1381="YES",IF(I1381=1,C1381,""),IF(I1381=1,C1381,IF(I1381=2,C1381,IF(I1381=0,"","")))) | AG1381: =(C1381*G1381)+(C1381*H1381)+(C1381*I1381) -> 0
AD1382: =IF(E1382="YES",IF(G1382=1,"",""),IF(G1382=1,C1382,IF(G1382=2,C1382,IF(G1382=0,"","")))) | AE1382: =IF(E1382="YES",IF(G1382=1,"",IF(H1382=1,C1382,"")),IF(H1382=1,C1382,IF(H1382=2,C1382,IF(H1382=0,"","")))) | AF1382: =IF(E1382="YES",IF(I1382=1,C1382,""),IF(I1382=1,C1382,IF(I1382=2,C1382,IF(I1382=0,"","")))) | AG1382: =(C1382*G1382)+(C1382*H1382)+(C1382*I1382) -> 0
AD1383: =IF(E1383="YES",IF(G1383=1,"",""),IF(G1383=1,C1383,IF(G1383=2,C1383,IF(G1383=0,"","")))) | AE1383: =IF(E1383="YES",IF(G1383=1,"",IF(H1383=1,C1383,"")),IF(H1383=1,C1383,IF(H1383=2,C1383,IF(H1383=0,"","")))) | AF1383: =IF(E1383="YES",IF(I1383=1,C1383,""),IF(I1383=1,C1383,IF(I1383=2,C1383,IF(I1383=0,"","")))) | AG1383: =(C1383*G1383)+(C1383*H1383)+(C1383*I1383) -> 0
AD1384: =IF(E1384="YES",IF(G1384=1,"",""),IF(G1384=1,C1384,IF(G1384=2,C1384,IF(G1384=0,"","")))) | AE1384: =IF(E1384="YES",IF(G1384=1,"",IF(H1384=1,C1384,"")),IF(H1384=1,C1384,IF(H1384=2,C1384,IF(H1384=0,"","")))) | AF1384: =IF(E1384="YES",IF(I1384=1,C1384,""),IF(I1384=1,C1384,IF(I1384=2,C1384,IF(I1384=0,"",""))))
AD1385: =IF(E1385="YES",IF(G1385=1,"",""),IF(G1385=1,C1385,IF(G1385=2,C1385,IF(G1385=0,"","")))) | AE1385: =IF(E1385="YES",IF(G1385=1,"",IF(H1385=1,C1385,"")),IF(H1385=1,C1385,IF(H1385=2,C1385,IF(H1385=0,"","")))) | AF1385: =IF(E1385="YES",IF(I1385=1,C1385,""),IF(I1385=1,C1385,IF(I1385=2,C1385,IF(I1385=0,"",""))))
AD1386: =IF(E1386="YES",IF(G1386=1,"",""),IF(G1386=1,C1386,IF(G1386=2,C1386,IF(G1386=0,"","")))) | AE1386: =IF(E1386="YES",IF(G1386=1,"",IF(H1386=1,C1386,"")),IF(H1386=1,C1386,IF(H1386=2,C1386,IF(H1386=0,"","")))) | AF1386: =IF(E1386="YES",IF(I1386=1,C1386,""),IF(I1386=1,C1386,IF(I1386=2,C1386,IF(I1386=0,"",""))))
AD1387: =IF(E1387="YES",IF(G1387=1,"",""),IF(G1387=1,C1387,IF(G1387=2,C1387,IF(G1387=0,"","")))) | AE1387: =IF(E1387="YES",IF(G1387=1,"",IF(H1387=1,C1387,"")),IF(H1387=1,C1387,IF(H1387=2,C1387,IF(H1387=0,"","")))) | AF1387: =IF(E1387="YES",IF(I1387=1,C1387,""),IF(I1387=1,C1387,IF(I1387=2,C1387,IF(I1387=0,"",""))))
AD1388: =IF(E1388="YES",IF(G1388=1,"",""),IF(G1388=1,C1388,IF(G1388=2,C1388,IF(G1388=0,"","")))) | AE1388: =IF(E1388="YES",IF(G1388=1,"",IF(H1388=1,C1388,"")),IF(H1388=1,C1388,IF(H1388=2,C1388,IF(H1388=0,"","")))) | AF1388: =IF(E1388="YES",IF(I1388=1,C1388,""),IF(I1388=1,C1388,IF(I1388=2,C1388,IF(I1388=0,"",""))))
AD1389: =IF(E1389="YES",IF(G1389=1,"",""),IF(G1389=1,C1389,IF(G1389=2,C1389,IF(G1389=0,"","")))) | AE1389: =IF(E1389="YES",IF(G1389=1,"",IF(H1389=1,C1389,"")),IF(H1389=1,C1389,IF(H1389=2,C1389,IF(H1389=0,"","")))) | AF1389: =IF(E1389="YES",IF(I1389=1,C1389,""),IF(I1389=1,C1389,IF(I1389=2,C1389,IF(I1389=0,"",""))))
AD1390: =IF(E1390="YES",IF(G1390=1,"",""),IF(G1390=1,C1390,IF(G1390=2,C1390,IF(G1390=0,"","")))) | AE1390: =IF(E1390="YES",IF(G1390=1,"",IF(H1390=1,C1390,"")),IF(H1390=1,C1390,IF(H1390=2,C1390,IF(H1390=0,"","")))) | AF1390: =IF(E1390="YES",IF(I1390=1,C1390,""),IF(I1390=1,C1390,IF(I1390=2,C1390,IF(I1390=0,"",""))))
AD1391: =IF(E1391="YES",IF(G1391=1,"",""),IF(G1391=1,C1391,IF(G1391=2,C1391,IF(G1391=0,"","")))) | AE1391: =IF(E1391="YES",IF(G1391=1,"",IF(H1391=1,C1391,"")),IF(H1391=1,C1391,IF(H1391=2,C1391,IF(H1391=0,"","")))) | AF1391: =IF(E1391="YES",IF(I1391=1,C1391,""),IF(I1391=1,C1391,IF(I1391=2,C1391,IF(I1391=0,"",""))))

Sheet House Count
A1: FULL ADDRESS (Upper Case) | B1: CITY | C1: STATE | D1: ZIP CODE | E1: Unit Number | F1: HOUSE TYPE | G1: Drop Type | H1: Servicable (Y/N) | I1: Serviceability Notes | J1: RES | K1: BUS
A2: 13316 INGE RD | B2: CHESTER | C2: VIRGINIA | D2: 23836 | F2: RES-SFU | G2: BURIED | H2: Y | J2: =IF('House Count'!H2="Y",IF('House Count'!F2="RES-SFU",1,IF('House Count'!F2="RES-MDU",1,IF('House Count'!F2="RES-HOA",1,0))),0) -> 1 | K2: =IF('House Count'!H2="Y",IF('House Count'!F2="COMM-SU",1,IF('House Count'!F2="COM-MTU",1,IF('House Count'!F2="ENT",1,0))),0) -> 0
A3: 814 EAST HUNDRED RD | B3: CHESTER | C3: VIRGINIA | D3: 23836 | F3: RES-SFU | G3: BURIED | H3: Y | J3: =IF('House Count'!H3="Y",IF('House Count'!F3="RES-SFU",1,IF('House Count'!F3="RES-MDU",1,IF('House Count'!F3="RES-HOA",1,0))),0) -> 1 | K3: =IF('House Count'!H3="Y",IF('House Count'!F3="COMM-SU",1,IF('House Count'!F3="COM-MTU",1,IF('House Count'!F3="ENT",1,0))),0) -> 0
A4: 571 EAST HUNDRED RD | B4: CHESTER | C4: VIRGINIA | D4: 23836 | F4: RES-SFU | G4: BURIED | H4: Y | J4: =IF('House Count'!H4="Y",IF('House Count'!F4="RES-SFU",1,IF('House Count'!F4="RES-MDU",1,IF('House Count'!F4="RES-HOA",1,0))),0) -> 1 | K4: =IF('House Count'!H4="Y",IF('House Count'!F4="COMM-SU",1,IF('House Count'!F4="COM-MTU",1,IF('House Count'!F4="ENT",1,0))),0) -> 0
A5: 361 EAST HUNDRED RD | B5: CHESTER | C5: VIRGINIA | D5: 23836 | F5: COMM-SU | G5: BURIED | H5: Y | J5: =IF('House Count'!H5="Y",IF('House Count'!F5="RES-SFU",1,IF('House Count'!F5="RES-MDU",1,IF('House Count'!F5="RES-HOA",1,0))),0) -> 0 | K5: =IF('House Count'!H5="Y",IF('House Count'!F5="COMM-SU",1,IF('House Count'!F5="COM-MTU",1,IF('House Count'!F5="ENT",1,0))),0) -> 1
A6: 355 EAST HUNDRED RD | B6: CHESTER | C6: VIRGINIA | D6: 23836 | F6: VL | G6: BURIED | H6: N | J6: =IF('House Count'!H6="Y",IF('House Count'!F6="RES-SFU",1,IF('House Count'!F6="RES-MDU",1,IF('House Count'!F6="RES-HOA",1,0))),0) -> 0 | K6: =IF('House Count'!H6="Y",IF('House Count'!F6="COMM-SU",1,IF('House Count'!F6="COM-MTU",1,IF('House Count'!F6="ENT",1,0))),0) -> 0
A7: 13312 BERMUDA ORCHARD LN | B7: CHESTER | C7: VIRGINIA | D7: 23836 | F7: VL | G7: BURIED | H7: N | J7: =IF('House Count'!H7="Y",IF('House Count'!F7="RES-SFU",1,IF('House Count'!F7="RES-MDU",1,IF('House Count'!F7="RES-HOA",1,0))),0) -> 0 | K7: =IF('House Count'!H7="Y",IF('House Count'!F7="COMM-SU",1,IF('House Count'!F7="COM-MTU",1,IF('House Count'!F7="ENT",1,0))),0) -> 0
A8: 630 EAST HUNDRED RD | B8: CHESTER | C8: VIRGINIA | D8: 23836 | F8: COMM-SU | G8: BURIED | H8: Y | J8: =IF('House Count'!H8="Y",IF('House Count'!F8="RES-SFU",1,IF('House Count'!F8="RES-MDU",1,IF('House Count'!F8="RES-HOA",1,0))),0) -> 0 | K8: =IF('House Count'!H8="Y",IF('House Count'!F8="COMM-SU",1,IF('House Count'!F8="COM-MTU",1,IF('House Count'!F8="ENT",1,0))),0) -> 1
A9: 570 EAST HUNDRED RD | B9: CHESTER | C9: VIRGINIA | D9: 23836 | F9: COMM-SU | G9: BURIED | H9: Y | J9: =IF('House Count'!H9="Y",IF('House Count'!F9="RES-SFU",1,IF('House Count'!F9="RES-MDU",1,IF('House Count'!F9="RES-HOA",1,0))),0) -> 0 | K9: =IF('House Count'!H9="Y",IF('House Count'!F9="COMM-SU",1,IF('House Count'!F9="COM-MTU",1,IF('House Count'!F9="ENT",1,0))),0) -> 1
A10: 2 EAST HUNDRED RD | B10: CHESTER | C10: VIRGINIA | D10: 23836 | F10: COMM-SU | G10: BURIED | H10: Y | J10: =IF('House Count'!H10="Y",IF('House Count'!F10="RES-SFU",1,IF('House Count'!F10="RES-MDU",1,IF('House Count'!F10="RES-HOA",1,0))),0) -> 0 | K10: =IF('House Count'!H10="Y",IF('House Count'!F10="COMM-SU",1,IF('House Count'!F10="COM-MTU",1,IF('House Count'!F10="ENT",1,0))),0) -> 1
A11: 108 EAST HUNDRED RD | B11: CHESTER | C11: VIRGINIA | D11: 23836 | F11: VL | G11: BURIED | H11: N | J11: =IF('House Count'!H11="Y",IF('House Count'!F11="RES-SFU",1,IF('House Count'!F11="RES-MDU",1,IF('House Count'!F11="RES-HOA",1,0))),0) -> 0 | K11: =IF('House Count'!H11="Y",IF('House Count'!F11="COMM-SU",1,IF('House Count'!F11="COM-MTU",1,IF('House Count'!F11="ENT",1,0))),0) -> 0
A12: 360 EAST HUNDRED RD | B12: CHESTER | C12: VIRGINIA | D12: 23836 | F12: VL | G12: BURIED | H12: N | J12: =IF('House Count'!H12="Y",IF('House Count'!F12="RES-SFU",1,IF('House Count'!F12="RES-MDU",1,IF('House Count'!F12="RES-HOA",1,0))),0) -> 0 | K12: =IF('House Count'!H12="Y",IF('House Count'!F12="COMM-SU",1,IF('House Count'!F12="COM-MTU",1,IF('House Count'!F12="ENT",1,0))),0) -> 0
A13: 13320 INGE RD | B13: CHESTER | C13: VIRGINIA | D13: 23836 | F13: RES-SFU | G13: BURIED | H13: Y | J13: =IF('House Count'!H13="Y",IF('House Count'!F13="RES-SFU",1,IF('House Count'!F13="RES-MDU",1,IF('House Count'!F13="RES-HOA",1,0))),0) -> 1 | K13: =IF('House Count'!H13="Y",IF('House Count'!F13="COMM-SU",1,IF('House Count'!F13="COM-MTU",1,IF('House Count'!F13="ENT",1,0))),0) -> 0
... A71: 348 EAST HUNDRED RD | B71: CHESTER | C71: VIRGINIA | D71: 23836 | F71: COMM-SU | G71: BURIED | H71: Y | J71: =IF('House Count'!H71="Y",IF('House Count'!F71="RES-SFU",1,IF('House Count'!F71="RES-MDU",1,IF('House Count'!F71="RES-HOA",1,0))),0) -> 0 | K71: =IF('House Count'!H71="Y",IF('House Count'!F71="COMM-SU",1,IF('House Count'!F71="COM-MTU",1,IF('House Count'!F71="ENT",1,0))),0) -> 1
J72: =IF('House Count'!H72="Y",IF('House Count'!F72="RES-SFU",1,IF('House Count'!F72="RES-MDU",1,IF('House Count'!F72="RES-HOA",1,0))),0) -> 0 | K72: =IF('House Count'!H72="Y",IF('House Count'!F72="COMM-SU",1,IF('House Count'!F72="COM-MTU",1,IF('House Count'!F72="ENT",1,0))),0) -> 0
J73: =IF('House Count'!H73="Y",IF('House Count'!F73="RES-SFU",1,IF('House Count'!F73="RES-MDU",1,IF('House Count'!F73="RES-HOA",1,0))),0) -> 0 | K73: =IF('House Count'!H73="Y",IF('House Count'!F73="COMM-SU",1,IF('House Count'!F73="COM-MTU",1,IF('House Count'!F73="ENT",1,0))),0) -> 0
J74: =IF('House Count'!H74="Y",IF('House Count'!F74="RES-SFU",1,IF('House Count'!F74="RES-MDU",1,IF('House Count'!F74="RES-HOA",1,0))),0) -> 0 | K74: =IF('House Count'!H74="Y",IF('House Count'!F74="COMM-SU",1,IF('House Count'!F74="COM-MTU",1,IF('House Count'!F74="ENT",1,0))),0) -> 0
J75: =IF('House Count'!H75="Y",IF('House Count'!F75="RES-SFU",1,IF('House Count'!F75="RES-MDU",1,IF('House Count'!F75="RES-HOA",1,0))),0) -> 0 | K75: =IF('House Count'!H75="Y",IF('House Count'!F75="COMM-SU",1,IF('House Count'!F75="COM-MTU",1,IF('House Count'!F75="ENT",1,0))),0) -> 0
J76: =IF('House Count'!H76="Y",IF('House Count'!F76="RES-SFU",1,IF('House Count'!F76="RES-MDU",1,IF('House Count'!F76="RES-HOA",1,0))),0) -> 0 | K76: =IF('House Count'!H76="Y",IF('House Count'!F76="COMM-SU",1,IF('House Count'!F76="COM-MTU",1,IF('House Count'!F76="ENT",1,0))),0) -> 0
J77: =IF('House Count'!H77="Y",IF('House Count'!F77="RES-SFU",1,IF('House Count'!F77="RES-MDU",1,IF('House Count'!F77="RES-HOA",1,0))),0) -> 0 | K77: =IF('House Count'!H77="Y",IF('House Count'!F77="COMM-SU",1,IF('House Count'!F77="COM-MTU",1,IF('House Count'!F77="ENT",1,0))),0) -> 0
J78: =IF('House Count'!H78="Y",IF('House Count'!F78="RES-SFU",1,IF('House Count'!F78="RES-MDU",1,IF('House Count'!F78="RES-HOA",1,0))),0) -> 0 | K78: =IF('House Count'!H78="Y",IF('House Count'!F78="COMM-SU",1,IF('House Count'!F78="COM-MTU",1,IF('House Count'!F78="ENT",1,0))),0) -> 0
J79: =IF('House Count'!H79="Y",IF('House Count'!F79="RES-SFU",1,IF('House Count'!F79="RES-MDU",1,IF('House Count'!F79="RES-HOA",1,0))),0) -> 0 | K79: =IF('House Count'!H79="Y",IF('House Count'!F79="COMM-SU",1,IF('House Count'!F79="COM-MTU",1,IF('House Count'!F79="ENT",1,0))),0) -> 0
J80: =IF('House Count'!H80="Y",IF('House Count'!F80="RES-SFU",1,IF('House Count'!F80="RES-MDU",1,IF('House Count'!F80="RES-HOA",1,0))),0) -> 0 | K80: =IF('House Count'!H80="Y",IF('House Count'!F80="COMM-SU",1,IF('House Count'!F80="COM-MTU",1,IF('House Count'!F80="ENT",1,0))),0) -> 0
J81: =IF('House Count'!H81="Y",IF('House Count'!F81="RES-SFU",1,IF('House Count'!F81="RES-MDU",1,IF('House Count'!F81="RES-HOA",1,0))),0) -> 0 | K81: =IF('House Count'!H81="Y",IF('House Count'!F81="COMM-SU",1,IF('House Count'!F81="COM-MTU",1,IF('House Count'!F81="ENT",1,0))),0) -> 0
J82: =IF('House Count'!H82="Y",IF('House Count'!F82="RES-SFU",1,IF('House Count'!F82="RES-MDU",1,IF('House Count'!F82="RES-HOA",1,0))),0) -> 0 | K82: =IF('House Count'!H82="Y",IF('House Count'!F82="COMM-SU",1,IF('House Count'!F82="COM-MTU",1,IF('House Count'!F82="ENT",1,0))),0) -> 0
J83: =IF('House Count'!H83="Y",IF('House Count'!F83="RES-SFU",1,IF('House Count'!F83="RES-MDU",1,IF('House Count'!F83="RES-HOA",1,0))),0) -> 0 | K83: =IF('House Count'!H83="Y",IF('House Count'!F83="COMM-SU",1,IF('House Count'!F83="COM-MTU",1,IF('House Count'!F83="ENT",1,0))),0) -> 0
... J1513: =IF('House Count'!H1513="Y",IF('House Count'!F1513="RES-SFU",1,IF('House Count'!F1513="RES-MDU",1,IF('House Count'!F1513="RES-HOA",1,0))),0) -> 0 | K1513: =IF('House Count'!H1513="Y",IF('House Count'!F1513="COMM-SU",1,IF('House Count'!F1513="COM-MTU",1,IF('House Count'!F1513="ENT",1,0))),0) -> 0

Sheet MEW
A1: Material Estimate Worksheet
A3: Move Order # | D3: Job Description: | F3: ='COVER SHEET'!B3 -> VIRGINIA
A4: Job #: | B4: ='COVER SHEET'!F4 -> CHST 02-01 | D4: Branch Plant: | H4: LUMOS Employee Signature | J4: Date
A5: Capital Bud. #: | D5: Engineer: | F5: ='COVER SHEET'!F2:G2 -> CHAD ROBERTSON
A6: Date: | D6: Tax District:
H7: Contractor Name & Signature | J7: Date
A8: Account | C8: Actual | D8: Reel | H8: Sub Total | I8: Material | J8: Quantity | K8: Document
A9: Code | B9: Quantity | C9: Quantity | D9: Number | E9: Item No. | F9: Description | G9: Cost | H9: Cost | I9: Trans Loc | J9: Returned | K9: Number
A10: {=_xlfn._xlws.FILTER(MATERIAL!A6:H341,(MATERIAL!B6:B341<>"")*(MATERIAL!B6:B341<>0)*(MATERIAL!B6:B341<>"-"))} -> O.FBR.BURD | B10: 7927 | C10: 0 | D10: 0 | E10: FIBGEN48ARMR | F10: 048 Loose Tube PN D-048-LA-8W-F12NS; 048ZUC-T4122D20; AT3CEH2YT-048 | G10: 0.31 | H10: 2457.37
A11: O.FBR.BURD | B11: 3394 | C11: 0 | D11: 0 | E11: FIBGEN96ARMR | F11: 096 Loose Tube PN D-096-LA-8W-F12NS; 096ZUC-T4122D20; AT3CEH2YT-096 | G11: 0.62 | H11: 2104.28
A12: O.FBR.BURD | B12: 5998 | C12: 0 | D12: 0 | E12: FIBGEN144RIB | F12: 144 Ribbon FIber PN 144EC5-14100D53 | G12: 0.98 | H12: 5878.04
A13: O.FBR.BURD | B13: 27 | C13: 0 | D13: 0 | E13: SPLMLTERMBOX | F13: MULTILINK TERM BOX 12"X20"X8" RNB-12208-1SL-C-PG-Y-S | G13: 166.09 | H13: 4484.43
A14: O.CONDUIT | B14: 14636 | C14: 0 | D14: 0 | E14: INDGEN125 | F14: INNERDUCT 1.25" ARNCO SDR 13.5 | G14: 0.29 | H14: 4244.44
A15: O.CONDUIT | B15: 22 | C15: 0 | D15: 0 | E15: SPLROUTEMARKER | F15: FIBER ROUTE MARKER SIGN | G15: 13.97 | H15: 307.34
A16: O.CONDUIT | B16: 13 | C16: 0 | D16: 0 | E16: PBXGENDRPBX | F16: NON-DOT/NON-TIER 22 - FLOWER POT 11"X11"X12" DROP BOX PN SGLB01211261 AU101512P00N-XX; 100007163; SGLB-0 | G16: 19 | H16: 247
A17: O.CONDUIT | B17: 16 | C17: 0 | D17: 0 | E17: PBXGEN13X24X18 | F17: TIER 22 (SPLT) 13"x24"x18" DEEP BULK VAULT SHIELD TIER 22 (33 750LB TEST LOAD) SELF-LOCK HEX-HEAD SECURITY LUMOS CUSTOM LOGO PN BULKU1324180066261 | G17: 191.4 | H17: 3062.4
A18: O.CONDUIT | B18: 18 | C18: 0 | D18: 0 | E18: PBXGEN17X30X24 | F18: TIER 22 (SM) 17"X30" 24" DEEP BULK VAULT SHIELD TIER 22 (33 750LB TEST LOAD) 1-PIECE LID SELF-LOCK HEX-HEAD SECURITY LUMOS CUSTOM LOGO PN BULKU1730240066261 | G18: 317 | H18: 5706
A19: O.CONDUIT | B19: 5 | C19: 0 | D19: 0 | E19: PBXGEN24X36X24 | F19: TIER 22 (MED) 24"X36" 24" DEEP BULK VAULT SHIELD TIER 22 (33 750LB TEST LOAD) 1-PIECE LID SELF-LOCK HEX SECURITY. LUMOS CUSTOM LOGO PN BULKU2436240066261 | G19: 429.74 | H19: 2148.7
A20: O.FBR.BURD | B20: 3 | C20: 0 | D20: 0 | E20: SPLCHNG5NPRI | F20: Primary Splitter Location-G5NS TerminalGreen Hornet Fiber Splice Closure - Terminal Base, G5N- 5"x11", Two (2) Splice Trays, Two (2) 2x8 Splitters bare leads only, No Grommets, No Brackets, No Ground G5NSTA2ES0NN0NNN | G20: 190.32 | H20: 570.96
A21: O.FBR.BURD | B21: 24 | C21: 0 | D21: 0 | E21: SPLCHNG5NSEC | F21: Secondary Splitter Location"Drop Terminal"Green Hornet Fiber Splice Closure, G5N- 5"x11", Splice Trays (3), SC/APC Bulkhead with 16 Ports, Two (2) 1x4 Splitters with SC/APC Connectors, No Grommets, No Brackets, No Ground G5NSTA2BA0NN0NNN | G21: 211.83 | H21: 5083.92
F70: Sub-Total | H70: =SUM(H10:H69) -> 36294.88 | I70: NOTES:
F71: Provisioning (10%) & Tax (5%) | H71: =H70*(MATERIAL!H1+MATERIAL!H2) -> 5444.232
F72: Total Material Cost | H72: =H70+H71 -> 41739.112
A74: Account Code | B74: Good | C74: Worthless | E74: Item No. | F74: Description of Material Recovered

Sheet CABLE TO 1X8 SPLICING
A1: CABLE_1
A3: OLT | E3: ADDRESS | F3: 1X8 SPLITTER NAME | G3: PORT 1 | H3: PORT 2 | I3: PORT 3 | J3: PORT 4 | K3: PORT 5 | L3: PORT 6 | M3: PORT 7 | N3: PORT 8
A5: 1
A6: 2
A7: 3
A8: 4
A9: 5
A10: 6
A11: 7
A12: 8
A13: 9
A14: 10
A15: 11
A16: 12
... A45: 41
A46: 42 | D46: 42 | E46: F 115 EAST HUNDRED RD | F46: OLT02_42P_CHSTVA | G46: OLT02_42P_CHSTVA, 1 (OLT02_42P_CHSTVA-1) | H46: OLT02_42P_CHSTVA, 2 (OLT02_42P_CHSTVA-2) | I46: OLT02_42P_CHSTVA, 3 (OLT02_42P_CHSTVA-3) | J46: OLT02_42P_CHSTVA, 4 (OLT02_42P_CHSTVA-4) | K46: OLT02_42P_CHSTVA, 5 (OLT02_42P_CHSTVA-5) | L46: OLT02_42P_CHSTVA, 6 (OLT02_42P_CHSTVA-6) | M46: OLT02_42P_CHSTVA, 7 (OLT02_42P_CHSTVA-7) | N46: OLT02_42P_CHSTVA, 8 (OLT02_42P_CHSTVA-8)
A47: 43
A48: 44
A49: 45
A50: 46
A51: 47
A52: 48
A53: 49
A54: 50
A55: 51
A56: 52
A57: 53
A58: 54
... A194: 190
D195: 191 | E195: F 431 EAST HUNDRED RD | F195: OLT02_191P_CHSTVA | G195: OLT02_191P_CHSTVA, 1 (OLT02_191P_CHSTVA-1) | H195: OLT02_191P_CHSTVA, 2 (OLT02_191P_CHSTVA-2) | I195: OLT02_191P_CHSTVA, 3 (OLT02_191P_CHSTVA-3) | J195: OLT02_191P_CHSTVA, 4 (OLT02_191P_CHSTVA-4) | K195: OLT02_191P_CHSTVA, 5 (OLT02_191P_CHSTVA-5) | L195: OLT02_191P_CHSTVA, 6 (OLT02_191P_CHSTVA-6) | M195: OLT02_191P_CHSTVA, 7 (OLT02_191P_CHSTVA-7) | N195: OLT02_191P_CHSTVA, 8 (OLT02_191P_CHSTVA-8)
D196: 192 | E196: F 351 EAST HUNDRED RD | F196: OLT02_192P_CHSTVA | G196: OLT02_192P_CHSTVA, 1 (OLT02_192P_CHSTVA-1) | H196: OLT02_192P_CHSTVA, 2 (OLT02_192P_CHSTVA-2) | I196: OLT02_192P_CHSTVA, 3 (OLT02_192P_CHSTVA-3) | J196: OLT02_192P_CHSTVA, 4 (OLT02_192P_CHSTVA-4) | K196: OLT02_192P_CHSTVA, 5 (OLT02_192P_CHSTVA-5) | L196: OLT02_192P_CHSTVA, 6 (OLT02_192P_CHSTVA-6) | M196: OLT02_192P_CHSTVA, 7 (OLT02_192P_CHSTVA-7) | N196: OLT02_192P_CHSTVA, 8 (OLT02_192P_CHSTVA-8)

Sheet SPLICING 1X8 TO 1X4 SPLITS
A1: 1X8 SPLITTER PLACEMENT
A2: 42 | E2: 42 | F2: F 115 EAST HUNDRED RD
A3: SPLITTER NAME | B3: T COUNT | C3: 1X4 PLACEMENT ADDRESS | D3: SPLIT | E3: SERVICING | F3: SERVICING | G3: SERVICING | H3: SERVICING
A5: OLT02_42P_1S_CHSTVA | B5: 1-4 | C5: F 350 E HUNDRED RD | D5: OLT02_42P_CHSTVA, 1 | F5: 360 EAST HUNDRED RD | G5: 13237 RIVERS BEND BLVD | H5: 350 EAST HUNDRED RD
A6: OLT02_42P_2S_CHSTVA | B6: 5-8 | C6: F 231 EAST HUNDRED RD | D6: OLT02_42P_CHSTVA, 2 | H6: 231 EAST HUNDRED RD
A7: OLT02_42P_3S_CHSTVA | B7: 9-12 | C7: F 221 EAST HUNDRED RD | D7: OLT02_42P_CHSTVA, 3 | G7: 13311 INGE RD | H7: 221 EAST HUNDRED RD
A8: OLT02_42P_4S_CHSTVA | B8: 13-16 | C8: F 3 EAST HUNDRED RD | D8: OLT02_42P_CHSTVA, 4 | G8: 1 EAST HUNDRED RD | H8: 3 EAST HUNDRED RD
A9: OLT02_42P_5S_CHSTVA | B9: 17-20 | C9: F 5 EAST HUNDRED RD | D9: OLT02_42P_CHSTVA, 5 | G9: 103 EAST HUNDRED RD | H9: 5 EAST HUNDRED RD
A10: OLT02_42P_6S_CHSTVA | B10: 21-24 | C10: F 101 EAST HUNDRED RD | D10: OLT02_42P_CHSTVA, 6 | G10: 13310 INGE RD | H10: 101 EAST HUNDRED RD
A11: OLT02_42P_7S_CHSTVA | B11: 25-28 | C11: F 13320 INGE RD | D11: OLT02_42P_CHSTVA, 7 | H11: 201 JOHNSON CREEK DR
A12: OLT02_42P_8S_CHSTVA | B12: 29-32 | C12: F 13320 INGE RD | D12: OLT02_42P_CHSTVA, 8 | E12: 13316 INGE RD | F12: 13320 INGE RD | G12: 13322 INGE RD | H12: 13330 INGE RD
A14: 1X8 SPLITTER PLACEMENT
A15: 191 | E15: 191 | F15: F 431 EAST HUNDRED RD
A16: SPLITTER NAME | B16: T COUNT | C16: 1X4 PLACEMENT ADDRESS | D16: SPLIT | E16: SERVICING | F16: SERVICING | G16: SERVICING | H16: SERVICING
A18: OLT02_191P_1S_CHSTVA | B18: 1-4 | C18: F 804 EAST HUNDRED RD | D18: OLT02_191P_CHSTVA, 1 | E18: 814 EAST HUNDRED RD | F18: 810 EAST HUNDRED RD | G18: 804 EAST HUNDRED RD | H18: 800 EAST HUNDRED RD
A19: OLT02_191P_2S_CHSTVA | B19: 5-8 | C19: F 13335 KINGSTON AVE | D19: OLT02_191P_CHSTVA, 2 | G19: 13341 KINGSTON AVE | H19: 13335 KINGSTON AVE
A20: OLT02_191P_3S_CHSTVA | B20: 9-12 | C20: F 13200 KINGSTON AVE | D20: OLT02_191P_CHSTVA, 3 | G20: 13201 KINGSTON AVE | H20: 13200 KINGSTON AVE
A21: OLT02_191P_4S_CHSTVA | B21: 13-16 | C21: F 551 EAST HUNDRED RD | D21: OLT02_191P_CHSTVA, 4 | E21: 571 EAST HUNDRED RD | F21: 561 EAST HUNDRED RD | G21: 551 EAST HUNDRED RD | H21: 531 E HUNDRED RD
A22: OLT02_191P_5S_CHSTVA | B22: 17-20 | C22: F 511 EAST HUNDRED RD | D22: OLT02_191P_CHSTVA, 5 | G22: 511 E HUNDRED RD | H22: 13201 BERMUDA ORCHARD LN
A23: OLT02_191P_6S_CHSTVA | B23: 21-24 | C23: F 361 EAST HUNDRED RD | D23: OLT02_191P_CHSTVA, 6 | E23: 361 EAST HUNDRED RD | F23: 363 EAST HUNDRED RD | G23: 353 EAST HUNDRED RD | H23: 351 EAST HUNDRED RD
A24: OLT02_191P_7S_CHSTVA | B24: 25-28 | C24: F 401 EAST HUNDRED RD | D24: OLT02_191P_CHSTVA, 7 | E24: 355 EAST HUNDRED RD | F24: 401 EAST HUNDRED RD | G24: 371 EAST HUNDRED RD | H24: 381 EAST HUNDRED RD
A25: OLT02_191P_8S_CHSTVA | B25: 29-32 | C25: F 431 EAST HUNDRED RD | D25: OLT02_191P_CHSTVA, 8 | E25: 13312 BERMUDA ORCHARD LN | F25: 13200 BERMUDA ORCHARD LN | G25: 431 EAST HUNDRED RD | H25: 421 EAST HUNDRED RD
A27: 1X8 SPLITTER PLACEMENT
A28: 192 | E28: 192 | F28: F 351 EAST HUNDRED RD
A29: SPLITTER NAME | B29: T COUNT | C29: 1X4 PLACEMENT ADDRESS | D29: SPLIT | E29: SERVICING | F29: SERVICING | G29: SERVICING | H29: SERVICING
A31: OLT02_192P_1S_CHSTVA | B31: 1-4 | C31: F 600 EAST HUNDRED RD | D31: OLT02_192P_CHSTVA, 1 | E31: 630 EAST HUNDRED RD | F31: 620 EAST HUNDRED RD | G31: 600 EAST HUNDRED RD | H31: 580 EAST HUNDRED RD
A32: OLT02_192P_2S_CHSTVA | B32: 5-8 | C32: F 540 EAST HUNDRED RD | D32: OLT02_192P_CHSTVA, 2 | E32: 570 EAST HUNDRED RD | F32: 560 EAST HUNDRED RD | G32: 540 EAST HUNDRED RD | H32: 530 EAST HUNDRED RD
A33: OLT02_192P_3S_CHSTVA | B33: 9-12 | C33: F 520 EAST HUNDRED RD | D33: OLT02_192P_CHSTVA, 3 | G33: 520 EAST HUNDRED RD | H33: 500 EAST HUNDRED RD
A34: OLT02_192P_4S_CHSTVA | B34: 13-16 | C34: F 380 EAST HUNDRED RD | D34: OLT02_192P_CHSTVA, 4 | F34: 374 EAST HUNDRED RD | G34: 380 EAST HUNDRED RD | H34: 370 EAST HUNDRED RD
A35: OLT02_192P_5S_CHSTVA | B35: 17-20 | C35: F 100 EAST HUNDRED RD | D35: OLT02_192P_CHSTVA, 5 | E35: 2 EAST HUNDRED RD | F35: 10 EAST HUNDRED RD | G35: 20 EAST HUNDRED RD | H35: 100 E HUNDRED RD
A36: OLT02_192P_6S_CHSTVA | B36: 21-24 | C36: F 116 EAST HUNDRED RD | D36: OLT02_192P_CHSTVA, 6 | E36: 108 EAST HUNDRED RD | F36: 116 E HUNDRED RD | G36: 204 E HUNDRED RD | H36: 200 E HUNDRED RD
A37: OLT02_192P_7S_CHSTVA | B37: 25-28 | C37: F 200 EAST HUNDRED RD | D37: OLT02_192P_CHSTVA, 7 | F37: 210 E HUNDRED RD | G37: 220 E HUNDRED RD | H37: 230 E HUNDRED RD
A38: OLT02_192P_8S_CHSTVA | B38: 29-32 | C38: F 348 EAST HUNDRED RD | D38: OLT02_192P_CHSTVA, 8 | F38: 13241 RIVERS BEND BLVD | G38: 13301 RIVERS BEND BLVD | H38: 348 EAST HUNDRED RD

Sheet FINAL ADDRESS LIST
A1: ADDRESS | B1: UNIT | C1: City | D1: STATE | E1: ZIP | F1: BUSINESS/RESIDENTIAL | G1: House Type | H1: Servicablity
A2: ='House Count'!A2 -> 13316 INGE RD | B2: ='House Count'!E2 -> 0 | C2: ='House Count'!B2 -> CHESTER | D2: ='House Count'!C2 -> VIRGINIA | E2: ='House Count'!D2 -> 23836 | F2: =IF(G2="RES-SFU","RESIDENTIAL",IF(G2="RES-HOA","RESIDENTIAL",IF(G2="RES-MDU","RESIDENTIAL",IF(G2="COMM-SU","BUSINESS",IF(G2="COM-MTU","BUSINESS",IF(G2="ENT","BUSINESS","")))))) -> RESIDENTIAL | G2: ='House Count'!F2 -> RES-SFU | H2: ='House Count'!H2 -> Y
A3: ='House Count'!A3 -> 814 EAST HUNDRED RD | B3: ='House Count'!E3 -> 0 | C3: ='House Count'!B3 -> CHESTER | D3: ='House Count'!C3 -> VIRGINIA | E3: ='House Count'!D3 -> 23836 | F3: =IF(G3="RES-SFU","RESIDENTIAL",IF(G3="RES-HOA","RESIDENTIAL",IF(G3="RES-MDU","RESIDENTIAL",IF(G3="COMM-SU","BUSINESS",IF(G3="COM-MTU","BUSINESS",IF(G3="ENT","BUSINESS","")))))) -> RESIDENTIAL | G3: ='House Count'!F3 -> RES-SFU | H3: ='House Count'!H3 -> Y
A4: ='House Count'!A4 -> 571 EAST HUNDRED RD | B4: ='House Count'!E4 -> 0 | C4: ='House Count'!B4 -> CHESTER | D4: ='House Count'!C4 -> VIRGINIA | E4: ='House Count'!D4 -> 23836 | F4: =IF(G4="RES-SFU","RESIDENTIAL",IF(G4="RES-HOA","RESIDENTIAL",IF(G4="RES-MDU","RESIDENTIAL",IF(G4="COMM-SU","BUSINESS",IF(G4="COM-MTU","BUSINESS",IF(G4="ENT","BUSINESS","")))))) -> RESIDENTIAL | G4: ='House Count'!F4 -> RES-SFU | H4: ='House Count'!H4 -> Y
A5: ='House Count'!A5 -> 361 EAST HUNDRED RD | B5: ='House Count'!E5 -> 0 | C5: ='House Count'!B5 -> CHESTER | D5: ='House Count'!C5 -> VIRGINIA | E5: ='House Count'!D5 -> 23836 | F5: =IF(G5="RES-SFU","RESIDENTIAL",IF(G5="RES-HOA","RESIDENTIAL",IF(G5="RES-MDU","RESIDENTIAL",IF(G5="COMM-SU","BUSINESS",IF(G5="COM-MTU","BUSINESS",IF(G5="ENT","BUSINESS","")))))) -> BUSINESS | G5: ='House Count'!F5 -> COMM-SU | H5: ='House Count'!H5 -> Y
A6: ='House Count'!A6 -> 355 EAST HUNDRED RD | B6: ='House Count'!E6 -> 0 | C6: ='House Count'!B6 -> CHESTER | D6: ='House Count'!C6 -> VIRGINIA | E6: ='House Count'!D6 -> 23836 | F6: =IF(G6="RES-SFU","RESIDENTIAL",IF(G6="RES-HOA","RESIDENTIAL",IF(G6="RES-MDU","RESIDENTIAL",IF(G6="COMM-SU","BUSINESS",IF(G6="COM-MTU","BUSINESS",IF(G6="ENT","BUSINESS","")))))) | G6: ='House Count'!F6 -> VL | H6: ='House Count'!H6 -> N
A7: ='House Count'!A7 -> 13312 BERMUDA ORCHARD LN | B7: ='House Count'!E7 -> 0 | C7: ='House Count'!B7 -> CHESTER | D7: ='House Count'!C7 -> VIRGINIA | E7: ='House Count'!D7 -> 23836 | F7: =IF(G7="RES-SFU","RESIDENTIAL",IF(G7="RES-HOA","RESIDENTIAL",IF(G7="RES-MDU","RESIDENTIAL",IF(G7="COMM-SU","BUSINESS",IF(G7="COM-MTU","BUSINESS",IF(G7="ENT","BUSINESS","")))))) | G7: ='House Count'!F7 -> VL | H7: ='House Count'!H7 -> N
A8: ='House Count'!A8 -> 630 EAST HUNDRED RD | B8: ='House Count'!E8 -> 0 | C8: ='House Count'!B8 -> CHESTER | D8: ='House Count'!C8 -> VIRGINIA | E8: ='House Count'!D8 -> 23836 | F8: =IF(G8="RES-SFU","RESIDENTIAL",IF(G8="RES-HOA","RESIDENTIAL",IF(G8="RES-MDU","RESIDENTIAL",IF(G8="COMM-SU","BUSINESS",IF(G8="COM-MTU","BUSINESS",IF(G8="ENT","BUSINESS","")))))) -> BUSINESS | G8: ='House Count'!F8 -> COMM-SU | H8: ='House Count'!H8 -> Y
A9: ='House Count'!A9 -> 570 EAST HUNDRED RD | B9: ='House Count'!E9 -> 0 | C9: ='House Count'!B9 -> CHESTER | D9: ='House Count'!C9 -> VIRGINIA | E9: ='House Count'!D9 -> 23836 | F9: =IF(G9="RES-SFU","RESIDENTIAL",IF(G9="RES-HOA","RESIDENTIAL",IF(G9="RES-MDU","RESIDENTIAL",IF(G9="COMM-SU","BUSINESS",IF(G9="COM-MTU","BUSINESS",IF(G9="ENT","BUSINESS","")))))) -> BUSINESS | G9: ='House Count'!F9 -> COMM-SU | H9: ='House Count'!H9 -> Y
A10: ='House Count'!A10 -> 2 EAST HUNDRED RD | B10: ='House Count'!E10 -> 0 | C10: ='House Count'!B10 -> CHESTER | D10: ='House Count'!C10 -> VIRGINIA | E10: ='House Count'!D10 -> 23836 | F10: =IF(G10="RES-SFU","RESIDENTIAL",IF(G10="RES-HOA","RESIDENTIAL",IF(G10="RES-MDU","RESIDENTIAL",IF(G10="COMM-SU","BUSINESS",IF(G10="COM-MTU","BUSINESS",IF(G10="ENT","BUSINESS","")))))) -> BUSINESS | G10: ='House Count'!F10 -> COMM-SU | H10: ='House Count'!H10 -> Y
A11: ='House Count'!A11 -> 108 EAST HUNDRED RD | B11: ='House Count'!E11 -> 0 | C11: ='House Count'!B11 -> CHESTER | D11: ='House Count'!C11 -> VIRGINIA | E11: ='House Count'!D11 -> 23836 | F11: =IF(G11="RES-SFU","RESIDENTIAL",IF(G11="RES-HOA","RESIDENTIAL",IF(G11="RES-MDU","RESIDENTIAL",IF(G11="COMM-SU","BUSINESS",IF(G11="COM-MTU","BUSINESS",IF(G11="ENT","BUSINESS","")))))) | G11: ='House Count'!F11 -> VL | H11: ='House Count'!H11 -> N
A12: ='House Count'!A12 -> 360 EAST HUNDRED RD | B12: ='House Count'!E12 -> 0 | C12: ='House Count'!B12 -> CHESTER | D12: ='House Count'!C12 -> VIRGINIA | E12: ='House Count'!D12 -> 23836 | F12: =IF(G12="RES-SFU","RESIDENTIAL",IF(G12="RES-HOA","RESIDENTIAL",IF(G12="RES-MDU","RESIDENTIAL",IF(G12="COMM-SU","BUSINESS",IF(G12="COM-MTU","BUSINESS",IF(G12="ENT","BUSINESS","")))))) | G12: ='House Count'!F12 -> VL | H12: ='House Count'!H12 -> N
A13: ='House Count'!A13 -> 13320 INGE RD | B13: ='House Count'!E13 -> 0 | C13: ='House Count'!B13 -> CHESTER | D13: ='House Count'!C13 -> VIRGINIA | E13: ='House Count'!D13 -> 23836 | F13: =IF(G13="RES-SFU","RESIDENTIAL",IF(G13="RES-HOA","RESIDENTIAL",IF(G13="RES-MDU","RESIDENTIAL",IF(G13="COMM-SU","BUSINESS",IF(G13="COM-MTU","BUSINESS",IF(G13="ENT","BUSINESS","")))))) -> RESIDENTIAL | G13: ='House Count'!F13 -> RES-SFU | H13: ='House Count'!H13 -> Y
... A1500: ='House Count'!A1500 -> 0 | B1500: ='House Count'!E1500 -> 0 | C1500: ='House Count'!B1500 -> 0 | D1500: ='House Count'!C1500 -> 0 | E1500: ='House Count'!D1500 -> 0 | F1500: =IF(G1500="RES-SFU","RESIDENTIAL",IF(G1500="RES-HOA","RESIDENTIAL",IF(G1500="RES-MDU","RESIDENTIAL",IF(G1500="COMM-SU","BUSINESS",IF(G1500="COM-MTU","BUSINESS",IF(G1500="ENT","BUSINESS","")))))) | G1500: ='House Count'!F1500 -> 0 | H1500: ='House Count'!H1500 -> 0

Sheet PERMITS
A1: PERMITS WORKSHEET
A3: DOT | J3: MUNICIPAL
A4: NAME | C4: DESCRIPTION | G4: AMOUNT | J4: NAME | L4: DESCRIPTION | P4: AMOUNT
G5: 0 | L5: CITY | P5: 500
L6: COUNTY | P6: 500
A20: RR | J20: EASEMENTS
A21: NAME | C21: DESCRIPTION | G21: AMOUNT | J21: NAME | L21: DESCRIPTION | P21: AMOUNT
G22: 0
A37: POLE | J37: THIRD-PARTY SPLICING
A38: NAME | C38: DESCRIPTION | G38: AMOUNT | J38: Number | L38: DESCRIPTION | P38: AMOUNT
G39: 0
A54: OTHER | J54: CELL SITE
A55: NAME | C55: DESCRIPTION | G55: AMOUNT | J55: NAME | L55: DESCRIPTION | P55: AMOUNT
C56: CONTINGENT LABOR | G56: 10000
A70: 0 | C70: MISC Access Equipment and install charge | G70: =A70*1350 -> 0
A72: TRAFFIC CONTROL
A73: NAME | C73: DESCRIPTION | L73: Price | N73: Unit | O73: Quantity | P73: AMOUNT
A74: Standard Flagging Operation | C74: Includes up to 2 crew members, 1 AWP work truck with rotating lights, 8 advanced warning signs, 40 cones and up to 8 hours on site with mobilization. | L74: 578.2 | N74: Daily | P74: =SUM(O74*L74) -> 0
A76: Standard Lane Closure- No TMA | C76: Includes up to 2 crew members, 1 AWP work truck with rotating lights, 1 arrow board, 10 advanced warning signs, 70 cones and up to 8 hours on site with mobilization. | L76: 676.2 | N76: Daily | P76: =SUM(O76*L76) -> 0
A78: Standard Shoulder Closure - No TMA | C78: Includes up to 2 crew members, 1 AWP work truck with rotating lights, 6 advanced warning signs, 40 cones and up to 8 hours on site with mobilization. | L78: 578.2 | N78: Daily | P78: =SUM(O78*L78) -> 0
A80: TMA | C80: Truck Mounted Attenuator (TMA)/Crash Truck,(Driver is extra, see below for hourly rate) | L80: 350 | N80: Daily | P80: =SUM(O80*L80) -> 0
A82: Traffic Control Technical | C82: Provide one additional traffic control technician as needed. | L82: 32.7 | N82: Hourly | P82: =SUM(O82*L82) -> 0
A84: MISC | P84: =SUM(O84*L84) -> 0
A86: MISC | P86: =SUM(O86*L86) -> 0
A88: Total Daily Cost of Traffic Control | P88: =SUM(P74:P87) -> 0

Sheet Ring splicing
A1: ERPS
A3: 1 | C3: 13 | E3: 25 | G3: 37 | I3: 49 | K3: 61 | M3: 73 | O3: 85 | Q3: 97 | S3: 109 | U3: 121 | W3: 133 | Y3: 145 | AA3: 157 | AC3: 169 | AE3: 181 | AG3: 193 | AI3: 205 | AK3: 217 | AM3: 229 | AO3: 241 | AQ3: 253 | AS3: 265 | AU3: 277
A4: 2 | C4: 14 | E4: 26 | G4: 38 | I4: 50 | K4: 62 | M4: 74 | O4: 86 | Q4: 98 | S4: 110 | U4: 122 | W4: 134 | Y4: 146 | AA4: 158 | AC4: 170 | AE4: 182 | AG4: 194 | AI4: 206 | AK4: 218 | AM4: 230 | AO4: 242 | AQ4: 254 | AS4: 266 | AU4: 278
A5: 3 | C5: 15 | E5: 27 | G5: 39 | I5: 51 | K5: 63 | M5: 75 | O5: 87 | Q5: 99 | S5: 111 | U5: 123 | W5: 135 | Y5: 147 | AA5: 159 | AC5: 171 | AE5: 183 | AG5: 195 | AI5: 207 | AK5: 219 | AM5: 231 | AO5: 243 | AQ5: 255 | AS5: 267 | AU5: 279
A6: 4 | C6: 16 | E6: 28 | G6: 40 | I6: 52 | K6: 64 | M6: 76 | O6: 88 | Q6: 100 | S6: 112 | U6: 124 | W6: 136 | Y6: 148 | AA6: 160 | AC6: 172 | AE6: 184 | AG6: 196 | AI6: 208 | AK6: 220 | AM6: 232 | AO6: 244 | AQ6: 256 | AS6: 268 | AU6: 280
A7: 5 | C7: 17 | E7: 29 | G7: 41 | I7: 53 | K7: 65 | M7: 77 | O7: 89 | Q7: 101 | S7: 113 | U7: 125 | W7: 137 | Y7: 149 | AA7: 161 | AC7: 173 | AE7: 185 | AG7: 197 | AI7: 209 | AK7: 221 | AM7: 233 | AO7: 245 | AQ7: 257 | AS7: 269 | AU7: 281
A8: 6 | C8: 18 | E8: 30 | G8: 42 | I8: 54 | K8: 66 | M8: 78 | O8: 90 | Q8: 102 | S8: 114 | U8: 126 | W8: 138 | Y8: 150 | AA8: 162 | AC8: 174 | AE8: 186 | AG8: 198 | AI8: 210 | AK8: 222 | AM8: 234 | AO8: 246 | AQ8: 258 | AS8: 270 | AU8: 282
A9: 7 | C9: 19 | E9: 31 | G9: 43 | I9: 55 | K9: 67 | M9: 79 | O9: 91 | Q9: 103 | S9: 115 | U9: 127 | W9: 139 | Y9: 151 | AA9: 163 | AC9: 175 | AE9: 187 | AG9: 199 | AI9: 211 | AK9: 223 | AM9: 235 | AO9: 247 | AQ9: 259 | AS9: 271 | AU9: 283
A10: 8 | C10: 20 | E10: 32 | G10: 44 | I10: 56 | K10: 68 | M10: 80 | O10: 92 | Q10: 104 | S10: 116 | U10: 128 | W10: 140 | Y10: 152 | AA10: 164 | AC10: 176 | AE10: 188 | AG10: 200 | AI10: 212 | AK10: 224 | AM10: 236 | AO10: 248 | AQ10: 260 | AS10: 272 | AU10: 284
A11: 9 | C11: 21 | E11: 33 | G11: 45 | I11: 57 | K11: 69 | M11: 81 | O11: 93 | Q11: 105 | S11: 117 | U11: 129 | W11: 141 | Y11: 153 | AA11: 165 | AC11: 177 | AE11: 189 | AG11: 201 | AI11: 213 | AK11: 225 | AM11: 237 | AO11: 249 | AQ11: 261 | AS11: 273 | AU11: 285
A12: 10 | C12: 22 | E12: 34 | G12: 46 | I12: 58 | K12: 70 | M12: 82 | O12: 94 | Q12: 106 | S12: 118 | U12: 130 | W12: 142 | Y12: 154 | AA12: 166 | AC12: 178 | AE12: 190 | AG12: 202 | AI12: 214 | AK12: 226 | AM12: 238 | AO12: 250 | AQ12: 262 | AS12: 274 | AU12: 286
A13: 11 | C13: 23 | E13: 35 | G13: 47 | I13: 59 | K13: 71 | M13: 83 | O13: 95 | Q13: 107 | S13: 119 | U13: 131 | W13: 143 | Y13: 155 | AA13: 167 | AC13: 179 | AE13: 191 | AG13: 203 | AI13: 215 | AK13: 227 | AM13: 239 | AO13: 251 | AQ13: 263 | AS13: 275 | AU13: 287
A14: 12 | C14: 24 | E14: 36 | G14: 48 | I14: 60 | K14: 72 | M14: 84 | O14: 96 | Q14: 108 | S14: 120 | U14: 132 | W14: 144 | Y14: 156 | AA14: 168 | AC14: 180 | AE14: 192 | AG14: 204 | AI14: 216 | AK14: 228 | AM14: 240 | AO14: 252 | AQ14: 264 | AS14: 276 | AU14: 288
B15: CISCO | D15: CISCO | F15: CISCO | H15: CISCO | J15: CISCO | L15: CISCO | N15: CISCO | P15: CISCO | R15: CISCO | T15: CISCO | V15: CISCO | X15: CISCO | Z15: CISCO | AB15: CISCO | AD15: CISCO | AF15: CISCO | AH15: CISCO | AJ15: CISCO | AL15: CISCO | AN15: CISCO | AP15: CISCO | AR15: CISCO | AT15: CISCO | AV15: CISCO
A18: FIBER ALLOTMENT | AK18: N008 FIBER ALLOTMENT
A20: 1 | C20: 13 | E20: 25 | G20: 37 | I20: 49 | K20: 61 | M20: 73 | O20: 85 | Q20: 97 | S20: 109 | U20: 121 | W20: 133 | Y20: 145 | AA20: 157 | AC20: 169 | AE20: 181 | AG20: 193 | AI20: 205 | AK20: 217 | AM20: 229 | AO20: 241 | AQ20: 253 | AS20: 265 | AU20: 277 | AW20: 289 | AY20: 301 | BA20: 313 | BC20: 325 | BE20: 337 | BG20: 349 | BI20: 361 | BK20: 373 | BM20: 385 | BO20: 397 | BQ20: 409 | BS20: 421
A21: 2 | C21: 14 | E21: 26 | G21: 38 | I21: 50 | K21: 62 | M21: 74 | O21: 86 | Q21: 98 | S21: 110 | U21: 122 | W21: 134 | Y21: 146 | AA21: 158 | AC21: 170 | AE21: 182 | AG21: 194 | AI21: 206 | AK21: 218 | AM21: 230 | AO21: 242 | AQ21: 254 | AS21: 266 | AU21: 278 | AW21: 290 | AY21: 302 | BA21: 314 | BC21: 326 | BE21: 338 | BG21: 350 | BI21: 362 | BK21: 374 | BM21: 386 | BO21: 398 | BQ21: 410 | BS21: 422
A22: 3 | C22: 15 | E22: 27 | G22: 39 | I22: 51 | K22: 63 | M22: 75 | O22: 87 | Q22: 99 | S22: 111 | U22: 123 | W22: 135 | Y22: 147 | AA22: 159 | AC22: 171 | AE22: 183 | AG22: 195 | AI22: 207 | AK22: 219 | AM22: 231 | AO22: 243 | AQ22: 255 | AS22: 267 | AU22: 279 | AW22: 291 | AY22: 303 | BA22: 315 | BC22: 327 | BE22: 339 | BG22: 351 | BI22: 363 | BK22: 375 | BM22: 387 | BO22: 399 | BQ22: 411 | BS22: 423
A23: 4 | C23: 16 | E23: 28 | G23: 40 | I23: 52 | K23: 64 | M23: 76 | O23: 88 | Q23: 100 | S23: 112 | U23: 124 | W23: 136 | Y23: 148 | AA23: 160 | AC23: 172 | AE23: 184 | AG23: 196 | AI23: 208 | AK23: 220 | AM23: 232 | AO23: 244 | AQ23: 256 | AS23: 268 | AU23: 280 | AW23: 292 | AY23: 304 | BA23: 316 | BC23: 328 | BE23: 340 | BG23: 352 | BI23: 364 | BK23: 376 | BM23: 388 | BO23: 400 | BQ23: 412 | BS23: 424
A24: 5 | C24: 17 | E24: 29 | G24: 41 | I24: 53 | K24: 65 | M24: 77 | O24: 89 | Q24: 101 | S24: 113 | U24: 125 | W24: 137 | Y24: 149 | AA24: 161 | AC24: 173 | AE24: 185 | AG24: 197 | AI24: 209 | AK24: 221 | AM24: 233 | AO24: 245 | AQ24: 257 | AS24: 269 | AU24: 281 | AW24: 293 | AY24: 305 | BA24: 317 | BC24: 329 | BE24: 341 | BG24: 353 | BI24: 365 | BK24: 377 | BM24: 389 | BO24: 401 | BQ24: 413 | BS24: 425
A25: 6 | C25: 18 | E25: 30 | G25: 42 | I25: 54 | K25: 66 | M25: 78 | O25: 90 | Q25: 102 | S25: 114 | U25: 126 | W25: 138 | Y25: 150 | AA25: 162 | AC25: 174 | AE25: 186 | AG25: 198 | AI25: 210 | AK25: 222 | AM25: 234 | AO25: 246 | AQ25: 258 | AS25: 270 | AU25: 282 | AW25: 294 | AY25: 306 | BA25: 318 | BC25: 330 | BE25: 342 | BG25: 354 | BI25: 366 | BK25: 378 | BM25: 390 | BO25: 402 | BQ25: 414 | BS25: 426
A26: 7 | C26: 19 | E26: 31 | G26: 43 | I26: 55 | K26: 67 | M26: 79 | O26: 91 | Q26: 103 | S26: 115 | U26: 127 | W26: 139 | Y26: 151 | AA26: 163 | AC26: 175 | AE26: 187 | AG26: 199 | AI26: 211 | AK26: 223 | AM26: 235 | AO26: 247 | AQ26: 259 | AS26: 271 | AU26: 283 | AW26: 295 | AY26: 307 | BA26: 319 | BC26: 331 | BE26: 343 | BG26: 355 | BI26: 367 | BK26: 379 | BM26: 391 | BO26: 403 | BQ26: 415 | BS26: 427
A27: 8 | C27: 20 | E27: 32 | G27: 44 | I27: 56 | K27: 68 | M27: 80 | O27: 92 | Q27: 104 | S27: 116 | U27: 128 | W27: 140 | Y27: 152 | AA27: 164 | AC27: 176 | AE27: 188 | AG27: 200 | AI27: 212 | AK27: 224 | AM27: 236 | AO27: 248 | AQ27: 260 | AS27: 272 | AU27: 284 | AW27: 296 | AY27: 308 | BA27: 320 | BC27: 332 | BE27: 344 | BG27: 356 | BI27: 368 | BK27: 380 | BM27: 392 | BO27: 404 | BQ27: 416 | BS27: 428
A28: 9 | C28: 21 | E28: 33 | G28: 45 | I28: 57 | K28: 69 | M28: 81 | O28: 93 | Q28: 105 | S28: 117 | U28: 129 | W28: 141 | Y28: 153 | AA28: 165 | AC28: 177 | AE28: 189 | AG28: 201 | AI28: 213 | AK28: 225 | AM28: 237 | AO28: 249 | AQ28: 261 | AS28: 273 | AU28: 285 | AW28: 297 | AY28: 309 | BA28: 321 | BC28: 333 | BE28: 345 | BG28: 357 | BI28: 369 | BK28: 381 | BM28: 393 | BO28: 405 | BQ28: 417 | BS28: 429
A29: 10 | C29: 22 | E29: 34 | G29: 46 | I29: 58 | K29: 70 | M29: 82 | O29: 94 | Q29: 106 | S29: 118 | U29: 130 | W29: 142 | Y29: 154 | AA29: 166 | AC29: 178 | AE29: 190 | AG29: 202 | AI29: 214 | AK29: 226 | AM29: 238 | AO29: 250 | AQ29: 262 | AS29: 274 | AU29: 286 | AW29: 298 | AY29: 310 | BA29: 322 | BC29: 334 | BE29: 346 | BG29: 358 | BI29: 370 | BK29: 382 | BM29: 394 | BO29: 406 | BQ29: 418 | BS29: 430
A30: 11 | C30: 23 | E30: 35 | G30: 47 | I30: 59 | K30: 71 | M30: 83 | O30: 95 | Q30: 107 | S30: 119 | U30: 131 | W30: 143 | Y30: 155 | AA30: 167 | AC30: 179 | AE30: 191 | AG30: 203 | AI30: 215 | AK30: 227 | AM30: 239 | AO30: 251 | AQ30: 263 | AS30: 275 | AU30: 287 | AW30: 299 | AY30: 311 | BA30: 323 | BC30: 335 | BE30: 347 | BG30: 359 | BI30: 371 | BK30: 383 | BM30: 395 | BO30: 407 | BQ30: 419 | BS30: 431
A31: 12 | C31: 24 | E31: 36 | G31: 48 | I31: 60 | K31: 72 | M31: 84 | O31: 96 | Q31: 108 | S31: 120 | U31: 132 | W31: 144 | Y31: 156 | AA31: 168 | AC31: 180 | AE31: 192 | AG31: 204 | AI31: 216 | AK31: 228 | AM31: 240 | AO31: 252 | AQ31: 264 | AS31: 276 | AU31: 288 | AW31: 300 | AY31: 312 | BA31: 324 | BC31: 336 | BE31: 348 | BG31: 360 | BI31: 372 | BK31: 384 | BM31: 396 | BO31: 408 | BQ31: 420 | BS31: 432
B32: FDH | D32: FDH | F32: FDH | H32: FDH | J32: FDH | L32: FDH | N32: FDH | P32: FDH | R32: FDH | T32: FDH | V32: FDH | X32: FDH | Z32: FDH | AB32: FDH | AD32: FDH | AF32: FDH | AH32: FDH | AJ32: FDH | AL32: FDH | AN32: FDH | AP32: FDH | AR32: FDH | AT32: FDH | AV32: FDH | AX32: FDH | AZ32: FDH | BB32: FDH | BD32: FDH | BF32: FDH | BH32: FDH | BJ32: FDH | BL32: FDH | BN32: FDH | BP32: FDH | BR32: FDH | BT32: FDH
